{
  "timestamp": "2026-03-25T07:16:58.144342+00:00",
  "markets": {
    "will-russia-capture-kostyantynivka-by-march-31-872-578": {
      "volumeNum": 925262.9221030048,
      "volume24hr": 4828.473572999999,
      "lastTradePrice": 0.06
    },
    "will-russia-capture-lyman-by-march-31-2026-494": {
      "volumeNum": 679635.4409820011,
      "volume24hr": 11293.15214,
      "lastTradePrice": 0.046
    },
    "will-russia-capture-all-of-donetsk-oblast-by-march-31-2026": {
      "volumeNum": 284705.1864700003,
      "volume24hr": 78.12,
      "lastTradePrice": 0.001
    },
    "will-russia-capture-kostyantynivka-by-december-31-2026-936-942-271-276-578": {
      "volumeNum": 282083.7377320001,
      "volume24hr": 3060.4241750000006,
      "lastTradePrice": 0.87
    },
    "will-russia-enter-druzkhivka-by-june-30-933-897": {
      "volumeNum": 249222.50901599994,
      "volume24hr": 3017.4947009999996,
      "lastTradePrice": 0.21
    },
    "will-russia-capture-all-of-kupiansk-by-march-31": {
      "volumeNum": 243821.57639799922,
      "volume24hr": 3702.71,
      "lastTradePrice": 0.001
    },
    "will-russia-capture-sumy-by-march-31-2027": {
      "volumeNum": 235888.7016510002,
      "volume24hr": 955.720935,
      "lastTradePrice": 0.18
    },
    "will-russia-capture-all-of-stepnohirsk-by-march-31-2026-627": {
      "volumeNum": 231615.5657500001,
      "volume24hr": 1437.73,
      "lastTradePrice": 0.04
    },
    "will-russia-capture-all-of-vovchansk-by-march-31": {
      "volumeNum": 208630.19204199992,
      "volume24hr": 73,
      "lastTradePrice": 0.014
    },
    "will-russia-capture-all-of-prymorske-by-march-31-2026-597": {
      "volumeNum": 199026.086179,
      "volume24hr": 42831.19,
      "lastTradePrice": 0.003
    },
    "will-russia-enter-ternuvate-again-by-march-31": {
      "volumeNum": 168946.43177899971,
      "volume24hr": 87234.28284999997,
      "lastTradePrice": 0.21
    },
    "will-russia-capture-all-of-huliaipole-by-march-31": {
      "volumeNum": 154961.6355159998,
      "volume24hr": 1565.2004809999999,
      "lastTradePrice": 0.2
    },
    "will-russia-enter-dopropillia-by-june-30-122-495": {
      "volumeNum": 149585.0394929999,
      "volume24hr": 2234.763952,
      "lastTradePrice": 0.44
    },
    "will-russia-enter-sloviansk-by-june-30": {
      "volumeNum": 137046.7123549999,
      "volume24hr": 71.415651,
      "lastTradePrice": 0.23
    },
    "will-russia-capture-kostyantynivka-by-june-30-382-954": {
      "volumeNum": 113915.79036700002,
      "volume24hr": 3215.7144279999993,
      "lastTradePrice": 0.67
    },
    "will-russia-enter-kramatorsk-by-june-30-821-192": {
      "volumeNum": 107226.61230799998,
      "volume24hr": 269.575554,
      "lastTradePrice": 0.15
    },
    "will-russia-capture-kostyantynivka-by-april-30": {
      "volumeNum": 91060.5168000001,
      "volume24hr": 4030.781531,
      "lastTradePrice": 0.23
    },
    "will-russia-capture-all-of-lyman-by-december-31-2026": {
      "volumeNum": 90838.40128399998,
      "volume24hr": 6.72,
      "lastTradePrice": 0.72
    },
    "will-russia-enter-orikhiv-by-march-31": {
      "volumeNum": 90124.01027399996,
      "volume24hr": 356.71914999999996,
      "lastTradePrice": 0.022
    },
    "will-russia-enter-mykhailivka-by-april-30": {
      "volumeNum": 85851.60809900003,
      "volume24hr": 180.066956,
      "lastTradePrice": 0.21
    },
    "will-russia-capture-lyman-by-april-30-2026": {
      "volumeNum": 81366.52975800006,
      "volume24hr": 1967.1702440000001,
      "lastTradePrice": 0.18
    },
    "will-russia-enter-zaporizhia-by-june-30-845": {
      "volumeNum": 69543.785989,
      "volume24hr": 78.039541,
      "lastTradePrice": 0.07
    },
    "will-russia-enter-borova-by-march-31": {
      "volumeNum": 69018.89365100005,
      "volume24hr": 1088.93,
      "lastTradePrice": 0.042
    },
    "will-russia-enter-sumy-by-june-30-893-434": {
      "volumeNum": 67633.60305600002,
      "volume24hr": 60.413827999999995,
      "lastTradePrice": 0.06
    },
    "will-russia-capture-bilytske-by-march-31-2026": {
      "volumeNum": 66944.88066000002,
      "volume24hr": 1526.2308880000003,
      "lastTradePrice": 0.061
    },
    "will-russia-capture-lyman-by-june-30-2026-413": {
      "volumeNum": 61036.31854699999,
      "volume24hr": 3665.924333,
      "lastTradePrice": 0.51
    },
    "will-russia-capture-all-of-donetsk-oblast-by-june-30-2026": {
      "volumeNum": 55691.46920800002,
      "volume24hr": 830.314972,
      "lastTradePrice": 0.047
    },
    "will-russia-capture-havrylivka-by-april-30-2026": {
      "volumeNum": 51367.466346000016,
      "volume24hr": 28.18,
      "lastTradePrice": 0.07
    },
    "will-ukraine-recapture-crimean-territory-by-june-30-2026": {
      "volumeNum": 51188.53784099997,
      "volume24hr": 2.05128,
      "lastTradePrice": 0.026
    },
    "will-ukraine-re-enter-uspenivka-by-march-31": {
      "volumeNum": 51173.79344300023,
      "volume24hr": 2120.273612,
      "lastTradePrice": 0.06
    },
    "will-russia-capture-sofiivka-by-march-31": {
      "volumeNum": 44319.79408799998,
      "volume24hr": 102.88111,
      "lastTradePrice": 0.12
    },
    "will-russia-enter-verkhnia-tersa-by-march-31-2026": {
      "volumeNum": 39851.461843,
      "volume24hr": 80.465399,
      "lastTradePrice": 0.13
    },
    "will-russia-capture-kupiansk-vuzlovyi-by-march-31": {
      "volumeNum": 37709.566082999954,
      "volume24hr": 33.165586,
      "lastTradePrice": 0.011
    },
    "will-russia-enter-vozdvyzhivka-by-march-31": {
      "volumeNum": 36714.8974240001,
      "volume24hr": 183.150537,
      "lastTradePrice": 0.09
    },
    "will-russia-enter-kharkiv-by-june-30-967": {
      "volumeNum": 33346.764302,
      "volume24hr": 1.050416,
      "lastTradePrice": 0.05
    },
    "will-russia-capture-all-of-drobysheve-by-march-31": {
      "volumeNum": 32926.87558000002,
      "volume24hr": 258.24827700000003,
      "lastTradePrice": 0.031
    },
    "will-russia-enter-khatnie-by-march-31-2026": {
      "volumeNum": 30202.622010999992,
      "volume24hr": 1075.5977290000003,
      "lastTradePrice": 0.031
    },
    "will-russia-enter-novyi-donbas-by-march-31": {
      "volumeNum": 29777.634274999982,
      "volume24hr": 4099.101855000001,
      "lastTradePrice": 0.09
    },
    "will-russia-capture-toretske-by-march-31-2026": {
      "volumeNum": 29323.131004000035,
      "volume24hr": 1287.9612439999996,
      "lastTradePrice": 0.14
    },
    "will-russia-enter-serhiivka-by-march-31": {
      "volumeNum": 29087.109467000002,
      "volume24hr": 119.97,
      "lastTradePrice": 0.028
    },
    "will-russia-capture-all-of-kostyantynivka-by-june-30-2026": {
      "volumeNum": 28540.231569000014,
      "volume24hr": 1326.8064529999997,
      "lastTradePrice": 0.11
    },
    "will-russia-enter-pokrovskoe-by-march-31-2026": {
      "volumeNum": 26577.109453,
      "volume24hr": 555.37,
      "lastTradePrice": 0.013
    },
    "will-russia-capture-all-of-kupiansk-by-june-30": {
      "volumeNum": 25187.41139899999,
      "volume24hr": 10,
      "lastTradePrice": 0.1
    },
    "will-russia-capture-all-of-lyman-by-june-30-2026": {
      "volumeNum": 24271.71143999999,
      "volume24hr": 35.73,
      "lastTradePrice": 0.17
    },
    "will-russia-enter-stinky-by-march-31": {
      "volumeNum": 22406.130232000007,
      "volume24hr": 17.64,
      "lastTradePrice": 0.051
    },
    "will-russia-enter-orikhiv-by-june-30": {
      "volumeNum": 21457.475704999997,
      "volume24hr": 80.861241,
      "lastTradePrice": 0.38
    },
    "will-russia-capture-lyman-by-december-31-2026-774": {
      "volumeNum": 20264.020535000007,
      "volume24hr": 520.027029,
      "lastTradePrice": 0.8
    },
    "will-russia-capture-all-of-kostyantynivka-by-december-31-2026": {
      "volumeNum": 18361.84138,
      "volume24hr": 477.93555900000007,
      "lastTradePrice": 0.51
    },
    "will-russia-capture-all-of-huliaipole-by-april-30": {
      "volumeNum": 17998.673519999986,
      "volume24hr": 1957.23,
      "lastTradePrice": 0.73
    },
    "will-russia-enter-rai-oleksandrivka-by-march-31-2026": {
      "volumeNum": 15133.238807,
      "volume24hr": 34.09,
      "lastTradePrice": 0.06
    },
    "will-russia-capture-all-of-ternuvate-by-march-31-2026": {
      "volumeNum": 14579.944321000003,
      "volume24hr": 603.5000000000001,
      "lastTradePrice": 0.011
    },
    "will-russia-capture-bilytske-by-april-30-2026": {
      "volumeNum": 14132.366780000006,
      "volume24hr": 5087.487989,
      "lastTradePrice": 0.32
    },
    "will-russia-capture-all-of-stepnohirsk-by-april-30-2026": {
      "volumeNum": 14015.753660000013,
      "volume24hr": 467.92,
      "lastTradePrice": 0.22
    },
    "will-russia-capture-all-of-drobysheve-by-april-30": {
      "volumeNum": 12247.65544,
      "volume24hr": 63.22222,
      "lastTradePrice": 0.1
    },
    "will-ukraine-re-enter-maliivka-by-march-31": {
      "volumeNum": 10363.971144999998,
      "volume24hr": 16.19,
      "lastTradePrice": 0.11
    },
    "will-russia-capture-pokrovka-by-march-31": {
      "volumeNum": 9763.860903999996,
      "volume24hr": 85.019082,
      "lastTradePrice": 0.1
    },
    "will-russia-capture-sofiivka-by-april-30": {
      "volumeNum": 9210.509338999997,
      "volume24hr": 220.46286399999997,
      "lastTradePrice": 0.38
    },
    "will-russia-enter-dobropillia-by-april-30": {
      "volumeNum": 8852.081835,
      "volume24hr": 68.18611,
      "lastTradePrice": 0.15
    },
    "will-russia-enter-svitle-by-april-30": {
      "volumeNum": 8835.376817999995,
      "volume24hr": 199.129022,
      "lastTradePrice": 0.17
    },
    "will-russia-enter-shevchenko-by-march-31": {
      "volumeNum": 6091.930445,
      "volume24hr": 827.3090100000002,
      "lastTradePrice": 0.04
    },
    "will-russia-capture-all-of-ternuvate-by-april-30-2026": {
      "volumeNum": 5996.284724999999,
      "volume24hr": 236.53380400000003,
      "lastTradePrice": 0.11
    },
    "will-russia-enter-svitle-by-march-31": {
      "volumeNum": 5911.9080140000015,
      "volume24hr": 167.28,
      "lastTradePrice": 0.017
    },
    "will-russia-capture-all-of-prymorske-by-april-30-2026": {
      "volumeNum": 5065.148858999998,
      "volume24hr": 134.892066,
      "lastTradePrice": 0.14
    },
    "will-russia-enter-shevchenko-by-april-30": {
      "volumeNum": 4583.452201999998,
      "volume24hr": 4.794517,
      "lastTradePrice": 0.28
    },
    "will-russia-enter-malokaterynivka-by-march-31-2026": {
      "volumeNum": 4519.613458000001,
      "volume24hr": 237.84000000000003,
      "lastTradePrice": 0.036
    },
    "will-russia-enter-novyi-donbas-by-april-30": {
      "volumeNum": 4394.6437879999985,
      "volume24hr": 411.46,
      "lastTradePrice": 0.41
    },
    "will-russia-capture-all-of-vovchansk-by-april-30": {
      "volumeNum": 3904.276119000001,
      "volume24hr": 2.38095,
      "lastTradePrice": 0.18
    },
    "will-russia-enter-pokrovskoe-by-april-30-2026": {
      "volumeNum": 3828.593175000001,
      "volume24hr": 276.54,
      "lastTradePrice": 0.031
    },
    "will-russia-capture-serhiivka-by-april-30": {
      "volumeNum": 2200.1609410000005,
      "volume24hr": 1816.999337,
      "lastTradePrice": 0.08
    },
    "will-russia-enter-lyman-by-april-30": {
      "volumeNum": 2111.429724,
      "volume24hr": 1797.8827700000002,
      "lastTradePrice": 0.71
    },
    "will-russia-enter-novooleksandrivka-by-april-30-2026": {
      "volumeNum": 1701.75035,
      "volume24hr": 601.7570179999999,
      "lastTradePrice": 0.61
    },
    "will-russia-enter-khatnie-by-april-30-2026": {
      "volumeNum": 1694.4300000000003,
      "volume24hr": 7.44,
      "lastTradePrice": 0.09
    },
    "will-ukraine-re-enter-rodynske-by-april-30": {
      "volumeNum": 1509.703712,
      "volume24hr": 805.383782,
      "lastTradePrice": 0.47
    },
    "will-russia-enter-malokaterynivka-by-april-30-2026": {
      "volumeNum": 1457.7340409999997,
      "volume24hr": 123.14,
      "lastTradePrice": 0.08
    },
    "will-russia-enter-kindrashivka-by-march-31": {
      "volumeNum": 897.1012099999998,
      "volume24hr": 6.6180900000000005,
      "lastTradePrice": 0.32
    },
    "will-russia-enter-vasylivka-by-april-30-2026": {
      "volumeNum": 864.251899,
      "volume24hr": 432.388567,
      "lastTradePrice": 0.32
    },
    "will-russia-enter-novooleksandrivka-by-march-31-2026": {
      "volumeNum": 763.8833979999999,
      "volume24hr": 759.5118,
      "lastTradePrice": 0.09
    },
    "will-russia-enter-havrylivka-by-april-30-2026": {
      "volumeNum": 759.6119870000001,
      "volume24hr": 4.76,
      "lastTradePrice": 0.23
    },
    "will-russia-enter-vasylivka-by-march-31-2026": {
      "volumeNum": 314.204948,
      "volume24hr": 294.204948,
      "lastTradePrice": 0.04
    },
    "will-russia-enter-myrne-by-march-31-2026": {
      "volumeNum": 170.52313999999998,
      "volume24hr": 130.52314,
      "lastTradePrice": 0.04
    },
    "will-russia-enter-myrne-by-april-30-2026": {
      "volumeNum": 95.671577,
      "volume24hr": 52.631577,
      "lastTradePrice": 0.19
    },
    "will-russia-enter-serhiivka-by-april-30": {
      "volumeNum": 82.25640899999999,
      "volume24hr": 62.256409,
      "lastTradePrice": 0.19
    },
    "will-russia-enter-borova-by-april-30": {
      "volumeNum": 0,
      "volume24hr": 0,
      "lastTradePrice": 0.27
    },
    "will-russia-enter-krasnoiarske-by-march-31": {
      "volumeNum": 0,
      "volume24hr": 0,
      "lastTradePrice": 0.1
    },
    "will-russia-enter-kherson-by-june-30-645": {
      "volumeNum": 0,
      "volume24hr": 0,
      "lastTradePrice": 0.048
    },
    "will-russia-capture-viroliubivka-by-march-31": {
      "volumeNum": 0,
      "volume24hr": 0,
      "lastTradePrice": 0.014
    },
    "will-russia-enter-dovha-balka-by-march-31": {
      "volumeNum": 0,
      "volume24hr": 0,
      "lastTradePrice": 0.1
    },
    "will-russia-enter-dobropillia-by-march-31": {
      "volumeNum": 0,
      "volume24hr": 0,
      "lastTradePrice": 0.011
    },
    "will-russia-enter-havrylivka-by-march-31-2026": {
      "volumeNum": 0,
      "volume24hr": 0,
      "lastTradePrice": 0.1
    },
    "will-russia-enter-krasnopillya-by-april-30": {
      "volumeNum": 0,
      "volume24hr": 0,
      "lastTradePrice": 0.14
    },
    "will-ukraine-re-enter-obratne-or-temyrivka-by-march-31": {
      "volumeNum": 0,
      "volume24hr": 0,
      "lastTradePrice": 0.06
    },
    "will-russia-capture-havrylivka-by-march-31-2026": {
      "volumeNum": 0,
      "volume24hr": 0,
      "lastTradePrice": 0.019
    },
    "will-russia-capture-kindrativka-by-march-31": {
      "volumeNum": 0,
      "volume24hr": 0,
      "lastTradePrice": 0.04
    },
    "russia-x-ukraine-ceasefire-by-march-31-2026": {
      "volumeNum": 28171897.48697239,
      "volume24hr": 416226.60516100004,
      "lastTradePrice": 0.004
    },
    "russia-x-ukraine-ceasefire-before-2027": {
      "volumeNum": 12171577.300509049,
      "volume24hr": 27970.759615999967,
      "lastTradePrice": 0.34
    },
    "russia-x-ukraine-ceasefire-by-june-30-2026": {
      "volumeNum": 3575867.878673028,
      "volume24hr": 31001.431566,
      "lastTradePrice": 0.15
    },
    "putin-out-before-2027": {
      "volumeNum": 3151762.838622981,
      "volume24hr": 17575.388464000003,
      "lastTradePrice": 0.12
    },
    "will-putin-meet-with-zelenskyy-by-march-31-2026": {
      "volumeNum": 2479449.053016991,
      "volume24hr": 502.751,
      "lastTradePrice": 0.002
    },
    "will-russia-invade-a-nato-country-by-june-30-2026": {
      "volumeNum": 2217794.4275609986,
      "volume24hr": 5941.4230560000005,
      "lastTradePrice": 0.051
    },
    "zelenskyy-out-as-ukraine-president-before-2027": {
      "volumeNum": 1945310.4005390115,
      "volume24hr": 1576.0878250000003,
      "lastTradePrice": 0.21
    },
    "will-russia-test-a-nuclear-weapon-by-march-31-2026": {
      "volumeNum": 1189879.5756720048,
      "volume24hr": 2984.5120869999996,
      "lastTradePrice": 0.004
    },
    "ukraine-joins-nato-before-2027": {
      "volumeNum": 1113438.6900520008,
      "volume24hr": 264.29,
      "lastTradePrice": 0.036
    },
    "putin-out-as-president-of-russia-by-june-30": {
      "volumeNum": 969154.1859360001,
      "volume24hr": 17725.024783000004,
      "lastTradePrice": 0.038
    },
    "russia-x-ukraine-ceasefire-by-april-30-2026": {
      "volumeNum": 894586.4133140007,
      "volume24hr": 46709.636557000005,
      "lastTradePrice": 0.04
    },
    "will-trump-and-putin-not-meet-315-857-437-514": {
      "volumeNum": 756118.864516,
      "volume24hr": 71.17,
      "lastTradePrice": 0.825
    },
    "will-trump-and-putin-meet-next-in-russia-594-493-482": {
      "volumeNum": 537326.4188949997,
      "volume24hr": 179.57,
      "lastTradePrice": 0.01
    },
    "will-ukraine-agree-to-cede-territory-to-russia-before-2027": {
      "volumeNum": 519790.49471800146,
      "volume24hr": 1199.63,
      "lastTradePrice": 0.22
    },
    "zelenskyy-out-as-ukraine-president-by-march-31-2026": {
      "volumeNum": 500919.2611309993,
      "volume24hr": 2886.0400000000004,
      "lastTradePrice": 0.006
    },
    "will-trump-and-putin-meet-next-in-another-european-country-954-837-364": {
      "volumeNum": 500065.27507099975,
      "volume24hr": 6.57,
      "lastTradePrice": 0.028
    },
    "nato-x-russia-military-clash-by-march-31-2026": {
      "volumeNum": 488901.6299799998,
      "volume24hr": 5812.021666,
      "lastTradePrice": 0.005
    },
    "will-zelenskyy-talk-to-putin-by-march-31": {
      "volumeNum": 382516.51388900034,
      "volume24hr": 784.4245,
      "lastTradePrice": 0.005
    },
    "russia-x-ukraine-peace-parlay": {
      "volumeNum": 381237.4398350001,
      "volume24hr": 3107.55,
      "lastTradePrice": 0.14
    },
    "ukraine-signs-peace-deal-with-russia-by-march-31": {
      "volumeNum": 363097.6037210004,
      "volume24hr": 2978.59018,
      "lastTradePrice": 0.006
    },
    "will-zelenskyy-and-putin-meet-next-in-us": {
      "volumeNum": 346063.46738199994,
      "volume24hr": 34.482757,
      "lastTradePrice": 0.029
    },
    "will-the-us-test-a-nuclear-weapon-by-march-31-2026": {
      "volumeNum": 270828.52022299997,
      "volume24hr": 16443.954073,
      "lastTradePrice": 0.003
    },
    "ukraine-election-called-by-march-31-2026": {
      "volumeNum": 251290.66939399944,
      "volume24hr": 494.959272,
      "lastTradePrice": 0.001
    },
    "ukraine-officially-agrees-to-a-us-backed-ceasefire-framework-by-march-31-214": {
      "volumeNum": 226601.90610200015,
      "volume24hr": 135.24,
      "lastTradePrice": 0.011
    },
    "will-trump-meet-with-putin-by-march-31": {
      "volumeNum": 219740.69038900014,
      "volume24hr": 927.55,
      "lastTradePrice": 0.007
    },
    "will-trump-and-putin-meet-next-in-belarus-572": {
      "volumeNum": 213819.43108399987,
      "volume24hr": 183.34,
      "lastTradePrice": 0.01
    },
    "ukraine-election-held-by-june-30-2026-465-757": {
      "volumeNum": 204233.8317319997,
      "volume24hr": 108.775601,
      "lastTradePrice": 0.049
    },
    "will-trump-and-putin-meet-next-in-china-586-328": {
      "volumeNum": 204166.25092199998,
      "volume24hr": 143.07,
      "lastTradePrice": 0.016
    },
    "ukraine-election-called-by-june-30-2026-392": {
      "volumeNum": 203331.27600999997,
      "volume24hr": 118.99341100000001,
      "lastTradePrice": 0.13
    },
    "will-zelenskyy-and-putin-meet-next-in-belarus": {
      "volumeNum": 199455.02959899997,
      "volume24hr": 1800,
      "lastTradePrice": 0.009
    },
    "ukraine-signs-peace-deal-with-russia-before-2027": {
      "volumeNum": 180518.7738829998,
      "volume24hr": 335.198463,
      "lastTradePrice": 0.27
    },
    "ukraine-recognizes-russian-sovereignty-over-its-territory-by-june-30-2026": {
      "volumeNum": 180479.9640080003,
      "volume24hr": 67.705353,
      "lastTradePrice": 0.036
    },
    "nato-x-russia-military-clash-by-june-30-2026": {
      "volumeNum": 177517.8629419998,
      "volume24hr": 2399.867509,
      "lastTradePrice": 0.064
    },
    "ukraine-election-held-by-december-31-2026-344-142": {
      "volumeNum": 168385.04581799987,
      "volume24hr": 179.13,
      "lastTradePrice": 0.16
    },
    "will-russia-capture-slovainsk-by-2027": {
      "volumeNum": 152165.22114699997,
      "volume24hr": 20.869564,
      "lastTradePrice": 0.08
    },
    "will-putin-meet-with-zelenskyy-by-june-30-2026": {
      "volumeNum": 148090.91861899992,
      "volume24hr": 701.0601429999999,
      "lastTradePrice": 0.038
    },
    "will-us-withdraw-from-nato-before-2027": {
      "volumeNum": 143411.80022899996,
      "volume24hr": 571,
      "lastTradePrice": 0.074
    },
    "zelenskyy-out-as-ukraine-president-by-january-31-2026": {
      "volumeNum": 127306.76580599985,
      "volume24hr": 3824.4807469999996,
      "lastTradePrice": 0.07
    },
    "us-agrees-to-give-ukraine-security-guarantee-by-june-30": {
      "volumeNum": 125513.56122200008,
      "volume24hr": 555.94,
      "lastTradePrice": 0.15
    },
    "will-trump-and-putin-meet-next-in-a-gulf-country-733-116": {
      "volumeNum": 117279.22198799996,
      "volume24hr": 39.22,
      "lastTradePrice": 0.019
    },
    "will-trump-and-putin-meet-next-in-south-korea-582-297-268": {
      "volumeNum": 111568.86181100004,
      "volume24hr": 110,
      "lastTradePrice": 0.003
    },
    "will-trump-and-putin-meet-next-in-united-states-224-875-469": {
      "volumeNum": 109829.40072300001,
      "volume24hr": 3739,
      "lastTradePrice": 0.02
    },
    "will-zelenskyy-and-putin-meet-next-in-india-416-286": {
      "volumeNum": 108978.61664499999,
      "volume24hr": 25129.7,
      "lastTradePrice": 0.005
    },
    "will-zelenskyy-and-putin-meet-next-in-turkey": {
      "volumeNum": 108558.987468,
      "volume24hr": 409.22094,
      "lastTradePrice": 0.03
    },
    "european-country-agrees-to-give-ukraine-security-guarantee-by-june-30": {
      "volumeNum": 97700.293887,
      "volume24hr": 60.76461200000001,
      "lastTradePrice": 0.12
    },
    "natoeu-troops-fighting-in-ukraine-in-june-30-2026": {
      "volumeNum": 96432.77128600022,
      "volume24hr": 39.690586,
      "lastTradePrice": 0.044
    },
    "will-trump-send-tomahawk-to-ukraine-by-march-31": {
      "volumeNum": 93888.49708699997,
      "volume24hr": 904.142047,
      "lastTradePrice": 0.004
    },
    "will-trump-and-putin-meet-next-in-japan-711-288-527": {
      "volumeNum": 92640.25614699998,
      "volume24hr": 92.766,
      "lastTradePrice": 0.003
    },
    "will-zelenskyy-and-putin-not-meet": {
      "volumeNum": 86769.41247899993,
      "volume24hr": 442.236206,
      "lastTradePrice": 0.77
    },
    "will-zelenskyy-and-putin-meet-next-in-ukraine": {
      "volumeNum": 86215.02984500003,
      "volume24hr": 21690,
      "lastTradePrice": 0.005
    },
    "ukraine-agrees-to-limit-size-of-armed-forces-before-2027": {
      "volumeNum": 82817.55889100008,
      "volume24hr": 134.54,
      "lastTradePrice": 0.25
    },
    "will-zelenskyy-and-putin-meet-next-in-qatar-uae": {
      "volumeNum": 80932.99685200001,
      "volume24hr": 18362.33,
      "lastTradePrice": 0.028
    },
    "will-zelenskyy-and-putin-meet-next-in-switzerland-848-193": {
      "volumeNum": 72028.83074800002,
      "volume24hr": 539.460473,
      "lastTradePrice": 0.024
    },
    "eunato-country-announces-peacekeeping-force-in-ukraine-before-2027": {
      "volumeNum": 69073.58267999995,
      "volume24hr": 1503.697776,
      "lastTradePrice": 0.036
    },
    "ukraine-agrees-not-to-join-nato-before-2027": {
      "volumeNum": 68943.44187600003,
      "volume24hr": 152.278144,
      "lastTradePrice": 0.2
    },
    "ukraine-agrees-not-to-join-nato-by-march-31": {
      "volumeNum": 66197.70299400006,
      "volume24hr": 21.58,
      "lastTradePrice": 0.011
    },
    "ukraine-signs-peace-deal-with-russia-by-june-30": {
      "volumeNum": 63680.0736129999,
      "volume24hr": 1828.86299,
      "lastTradePrice": 0.1
    },
    "will-zelenskyy-and-putin-meet-next-in-kazakhstan-485-344": {
      "volumeNum": 61487.33191000001,
      "volume24hr": 5849.5376,
      "lastTradePrice": 0.006
    },
    "ukraine-peace-referendum-scheduled-by-june-30": {
      "volumeNum": 57649.92892299998,
      "volume24hr": 98.310055,
      "lastTradePrice": 0.17
    },
    "will-zelenskyy-and-putin-meet-next-in-russia": {
      "volumeNum": 55945.46049800003,
      "volume24hr": 70.1,
      "lastTradePrice": 0.013
    },
    "will-ukraine-agree-to-give-up-the-rest-of-donbas-before-2027": {
      "volumeNum": 46627.477901,
      "volume24hr": 110.643156,
      "lastTradePrice": 0.19
    },
    "will-zelenskyy-and-putin-meet-next-in-hungary": {
      "volumeNum": 36359.52587900008,
      "volume24hr": 229.8,
      "lastTradePrice": 0.022
    },
    "russia-x-ukraine-ceasefire-before-us-x-iran-ceasefire": {
      "volumeNum": 35410.59758100002,
      "volume24hr": 654.71,
      "lastTradePrice": 0.12
    },
    "will-russia-strike-kyiv-on-march-31-2026": {
      "volumeNum": 28026.704891000005,
      "volume24hr": 457.392856,
      "lastTradePrice": 0.16
    },
    "us-recognizes-russian-sovereignty-over-ukraine-before-2027": {
      "volumeNum": 25637.932293,
      "volume24hr": 27.77,
      "lastTradePrice": 0.18
    },
    "us-x-russia-nuclear-deal-by-june-30": {
      "volumeNum": 24041.632100000024,
      "volume24hr": 95.588822,
      "lastTradePrice": 0.1
    },
    "ukraine-officially-agrees-to-a-us-backed-ceasefire-framework-by-june-30": {
      "volumeNum": 19858.576892999976,
      "volume24hr": 91.99714,
      "lastTradePrice": 0.11
    },
    "ukraine-hits-moscow-by-march-31-2026": {
      "volumeNum": 19312.76979600002,
      "volume24hr": 1019.6700000000001,
      "lastTradePrice": 0.1
    },
    "ukraine-agrees-not-to-join-nato-by-june-30": {
      "volumeNum": 14464.026624999997,
      "volume24hr": 4.709545,
      "lastTradePrice": 0.11
    },
    "trump-putin-and-zelensky-meet-together-before-2027": {
      "volumeNum": 14087.135052000007,
      "volume24hr": 17.594928,
      "lastTradePrice": 0.24
    },
    "ukraine-recognizes-russian-sovereignty-over-its-territory-by-december-31-2026": {
      "volumeNum": 13821.964592000002,
      "volume24hr": 74.568176,
      "lastTradePrice": 0.12
    },
    "nato-x-russia-military-clash-by-december-31-2026-244": {
      "volumeNum": 13723.516644000005,
      "volume24hr": 173.607148,
      "lastTradePrice": 0.23
    },
    "russia-military-action-against-kyiv-municipality-by-march-23": {
      "volumeNum": 12600.429101,
      "volume24hr": 954.6980629999999,
      "lastTradePrice": 0.01
    },
    "ukraine-strikes-another-tanker-in-black-sea-by-march-31-2026": {
      "volumeNum": 10527.341055000004,
      "volume24hr": 33.120000000000005,
      "lastTradePrice": 0.17
    },
    "will-russia-rejoin-the-g7-before-2027": {
      "volumeNum": 8443.683024000002,
      "volume24hr": 148.214865,
      "lastTradePrice": 0.147
    },
    "ukraine-coup-attempt-by-june-30": {
      "volumeNum": 8178.139306000002,
      "volume24hr": 33.673332,
      "lastTradePrice": 0.05
    },
    "will-zelenskyy-talk-to-putin-by-december-31-992": {
      "volumeNum": 7554.1728440000015,
      "volume24hr": 52.772304,
      "lastTradePrice": 0.22
    },
    "trump-putin-and-zelensky-seen-together-before-2027": {
      "volumeNum": 6925.005922999998,
      "volume24hr": 4.347825,
      "lastTradePrice": 0.23
    },
    "nord-stream-pipeline-turned-on-before-2027": {
      "volumeNum": 5222.0661150000005,
      "volume24hr": 100,
      "lastTradePrice": 0.07
    },
    "putin-and-zelenskyy-shake-hands-by-june-30": {
      "volumeNum": 4848.308113,
      "volume24hr": 20.435176,
      "lastTradePrice": 0.036
    },
    "will-a-us-ally-get-a-nuke-before-2027": {
      "volumeNum": 3888.1865360000006,
      "volume24hr": 5,
      "lastTradePrice": 0.14
    },
    "eunato-country-announces-peacekeeping-force-in-ukraine-by-december-31": {
      "volumeNum": 3640.7859129999993,
      "volume24hr": 7.894735,
      "lastTradePrice": 0.19
    },
    "russia-military-action-against-kyiv-municipality-by-march-27-387": {
      "volumeNum": 188.591406,
      "volume24hr": 188.591406,
      "lastTradePrice": 0.42
    },
    "will-trump-and-putin-meet-next-in-switzerland-448-348": {
      "volumeNum": 0,
      "volume24hr": 0,
      "lastTradePrice": 0.003
    },
    "will-trump-and-putin-meet-next-in-australia-459-332-211": {
      "volumeNum": 0,
      "volume24hr": 0,
      "lastTradePrice": 0.002
    },
    "will-trump-and-putin-meet-next-in-another-country-313-781-734-447": {
      "volumeNum": 0,
      "volume24hr": 0,
      "lastTradePrice": 0.015
    },
    "will-trump-and-putin-meet-next-in-ukraine-328-474": {
      "volumeNum": 0,
      "volume24hr": 0,
      "lastTradePrice": 0.002
    },
    "will-zelenskyy-and-putin-meet-next-in-italy-vatican": {
      "volumeNum": 0,
      "volume24hr": 0,
      "lastTradePrice": 0.006
    },
    "will-zelenskyy-and-putin-meet-next-in-china": {
      "volumeNum": 0,
      "volume24hr": 0,
      "lastTradePrice": 0.008
    },
    "will-zelenskyy-and-putin-meet-next-in-saudi-arabia": {
      "volumeNum": 0,
      "volume24hr": 0,
      "lastTradePrice": 0.02
    },
    "ukraine-peace-referendum-passed-by-december-31-2026": {
      "volumeNum": 0,
      "volume24hr": 0,
      "lastTradePrice": 0.26
    },
    "ukraine-peace-referendum-scheduled-by-march-31": {
      "volumeNum": 0,
      "volume24hr": 0,
      "lastTradePrice": 0.024
    },
    "ukraine-strikes-another-tanker-in-black-sea-by-april-15-2026": {
      "volumeNum": 0,
      "volume24hr": 0,
      "lastTradePrice": 0
    },
    "ukraine-hits-moscow-by-april-15-2026": {
      "volumeNum": 0,
      "volume24hr": 0,
      "lastTradePrice": 0
    },
    "ukraine-hits-moscow-by-april-30-2026": {
      "volumeNum": 0,
      "volume24hr": 0,
      "lastTradePrice": 0
    },
    "will-trump-and-putin-meet-next-in-finland-772-412": {
      "volumeNum": 0,
      "volume24hr": 0,
      "lastTradePrice": 0.002
    },
    "will-trump-and-putin-meet-next-in-turkey-182-161-789": {
      "volumeNum": 0,
      "volume24hr": 0,
      "lastTradePrice": 0.012
    },
    "will-donald-trump-win-the-nobel-peace-prize-in-2026-382": {
      "volumeNum": 2299717.749922992,
      "volume24hr": 2167.812147,
      "lastTradePrice": 0.08
    },
    "will-unrwa-win-the-nobel-peace-prize-in-2026-983": {
      "volumeNum": 1577386.5450800052,
      "volume24hr": 14834.217551,
      "lastTradePrice": 0.033
    },
    "russia-ukraine-ceasefire-before-gta-vi-554": {
      "volumeNum": 1399373.852013997,
      "volume24hr": 3312.267478999998,
      "lastTradePrice": 0.55
    },
    "will-ukraine-win-eurovision-2026": {
      "volumeNum": 896337.6467139978,
      "volume24hr": 33636.905873999975,
      "lastTradePrice": 0.023
    },
    "will-greta-thunberg-win-the-nobel-peace-prize-in-2026-767": {
      "volumeNum": 872938.5707879956,
      "volume24hr": 5247.091924999998,
      "lastTradePrice": 0.029
    },
    "will-xi-jinping-win-the-nobel-peace-prize-in-2026": {
      "volumeNum": 705427.749451001,
      "volume24hr": 9636.109771000005,
      "lastTradePrice": 0.01
    },
    "will-mohammed-bin-salman-win-the-nobel-peace-prize-in-2026": {
      "volumeNum": 518941.91093800025,
      "volume24hr": 7939.905360999999,
      "lastTradePrice": 0.007
    },
    "will-ahmed-al-sharaa-win-the-nobel-peace-prize-in-2026": {
      "volumeNum": 514464.57549499924,
      "volume24hr": 7615.502862,
      "lastTradePrice": 0.009
    },
    "will-elon-musk-win-the-nobel-peace-prize-in-2026-756": {
      "volumeNum": 503320.56701199885,
      "volume24hr": 8169.798756999999,
      "lastTradePrice": 0.02
    },
    "will-vladimir-putin-win-the-nobel-peace-prize-in-2026-126": {
      "volumeNum": 481311.3666410001,
      "volume24hr": 515.231857,
      "lastTradePrice": 0.01
    },
    "will-charlie-kirk-win-the-nobel-peace-prize-in-2026": {
      "volumeNum": 444159.20143499895,
      "volume24hr": 11055.820926,
      "lastTradePrice": 0.021
    },
    "will-the-international-court-of-justice-win-the-nobel-peace-prize-in-2026-885": {
      "volumeNum": 421679.4785779996,
      "volume24hr": 13619.099485000004,
      "lastTradePrice": 0.033
    },
    "will-pope-leo-xiv-win-the-nobel-peace-prize-in-2026-698": {
      "volumeNum": 386420.56334999914,
      "volume24hr": 17882.36474,
      "lastTradePrice": 0.036
    },
    "will-volodymyr-zelensky-win-the-nobel-peace-prize-in-2026-637": {
      "volumeNum": 353665.51388300007,
      "volume24hr": 3239.8219360000003,
      "lastTradePrice": 0.135
    },
    "will-julian-assange-win-the-nobel-peace-prize-in-2026-899": {
      "volumeNum": 303253.4567079997,
      "volume24hr": 431.047055,
      "lastTradePrice": 0.018
    },
    "will-recep-tayyip-erdoan-win-the-nobel-peace-prize-in-2026": {
      "volumeNum": 296955.26306599996,
      "volume24hr": 3687.3035600000007,
      "lastTradePrice": 0.015
    },
    "will-benjamin-netanyahu-win-the-nobel-peace-prize-in-2026": {
      "volumeNum": 296127.9288179999,
      "volume24hr": 1002.1363999999999,
      "lastTradePrice": 0.007
    },
    "will-narendra-modi-win-the-nobel-peace-prize-in-2026": {
      "volumeNum": 277757.5253959999,
      "volume24hr": 368.95000000000005,
      "lastTradePrice": 0.022
    },
    "will-tamim-bin-hamad-al-thani-win-the-nobel-peace-prize-in-2026-755": {
      "volumeNum": 273074.6571850006,
      "volume24hr": 25868.68865799999,
      "lastTradePrice": 0.035
    },
    "will-vladimir-putin-be-the-next-leader-out-before-2027-919": {
      "volumeNum": 255737.722267,
      "volume24hr": 164.53,
      "lastTradePrice": 0.021
    },
    "will-khaled-mashal-win-the-nobel-peace-prize-in-2026-787": {
      "volumeNum": 182816.73611700005,
      "volume24hr": 22217.382954,
      "lastTradePrice": 0.013
    },
    "will-ukraine-qualify-for-the-2026-fifa-world-cup": {
      "volumeNum": 152163.2677160005,
      "volume24hr": 2369.215453999998,
      "lastTradePrice": 0.29
    },
    "will-antnio-guterres-win-the-nobel-peace-prize-in-2026-623": {
      "volumeNum": 124870.02670200002,
      "volume24hr": 725.95125,
      "lastTradePrice": 0.012
    },
    "will-any-european-country-expel-an-israeli-ambassador-by-march-31": {
      "volumeNum": 105562.57053999997,
      "volume24hr": 4350.932678,
      "lastTradePrice": 0.029
    }
  }
}