{
  "timestamp": "2026-03-14T04:51:56.085551+00:00",
  "markets": {
    "will-russia-capture-kostyantynivka-by-march-31-872-578": {
      "volumeNum": 861180.4663210037,
      "volume24hr": 2630.375785,
      "lastTradePrice": 0.05
    },
    "will-russia-capture-lyman-by-march-31-2026-494": {
      "volumeNum": 596584.6885620006,
      "volume24hr": 832.986131,
      "lastTradePrice": 0.09
    },
    "will-russia-capture-hryshyne-by-march-31-2026-299": {
      "volumeNum": 293083.4118450006,
      "volume24hr": 25671.568378999993,
      "lastTradePrice": 0.996
    },
    "will-russia-capture-all-of-donetsk-oblast-by-march-31-2026": {
      "volumeNum": 274035.24813800026,
      "volume24hr": 6782.489998999999,
      "lastTradePrice": 0.004
    },
    "will-russia-capture-kostyantynivka-by-december-31-2026-936-942-271-276-578": {
      "volumeNum": 263944.4125210001,
      "volume24hr": 433.238473,
      "lastTradePrice": 0.87
    },
    "will-russia-capture-all-of-kupiansk-by-march-31": {
      "volumeNum": 224045.6081829992,
      "volume24hr": 10957.91,
      "lastTradePrice": 0.009
    },
    "will-russia-capture-all-of-stepnohirsk-by-march-31-2026-627": {
      "volumeNum": 218673.04094300012,
      "volume24hr": 5636.418324999999,
      "lastTradePrice": 0.04
    },
    "will-russia-capture-sumy-by-march-31-2027": {
      "volumeNum": 216030.72414500004,
      "volume24hr": 185.98541699999998,
      "lastTradePrice": 0.17
    },
    "will-russia-capture-all-of-rodynske-by-march-31": {
      "volumeNum": 179329.10374600012,
      "volume24hr": 764.5185679999998,
      "lastTradePrice": 0.34
    },
    "will-russia-capture-all-of-vovchansk-by-march-31": {
      "volumeNum": 174047.67726899998,
      "volume24hr": 150.903318,
      "lastTradePrice": 0.037
    },
    "will-russia-capture-all-of-prymorske-by-march-31-2026-597": {
      "volumeNum": 131212.22544399998,
      "volume24hr": 142.52292699999998,
      "lastTradePrice": 0.044
    },
    "will-russia-enter-sloviansk-by-june-30": {
      "volumeNum": 126446.72090199997,
      "volume24hr": 2412.09,
      "lastTradePrice": 0.19
    },
    "will-russia-capture-hryshyne-by-march-15-2026-338": {
      "volumeNum": 125880.93445499991,
      "volume24hr": 43247.60550099999,
      "lastTradePrice": 0.993
    },
    "will-russia-enter-dopropillia-by-june-30-122-495": {
      "volumeNum": 123311.61685499996,
      "volume24hr": 601.7,
      "lastTradePrice": 0.59
    },
    "will-russia-capture-all-of-huliaipole-by-march-31": {
      "volumeNum": 109212.33596999997,
      "volume24hr": 945.648475,
      "lastTradePrice": 0.17
    },
    "will-russia-enter-druzkhivka-by-june-30-933-897": {
      "volumeNum": 96400.77547899997,
      "volume24hr": 510.69855500000006,
      "lastTradePrice": 0.26
    },
    "will-russia-capture-all-of-lyman-by-december-31-2026": {
      "volumeNum": 87477.52207999997,
      "volume24hr": 172.413792,
      "lastTradePrice": 0.71
    },
    "will-russia-enter-orikhiv-by-march-31": {
      "volumeNum": 86410.14702299998,
      "volume24hr": 594.615945,
      "lastTradePrice": 0.04
    },
    "will-russia-enter-mykhailivka-by-april-30": {
      "volumeNum": 85046.86131100003,
      "volume24hr": 5.304346,
      "lastTradePrice": 0.23
    },
    "will-russia-capture-kostyantynivka-by-june-30-382-954": {
      "volumeNum": 80268.19032499996,
      "volume24hr": 1450.313226,
      "lastTradePrice": 0.69
    },
    "will-russia-capture-kostyantynivka-by-april-30": {
      "volumeNum": 71343.19622699995,
      "volume24hr": 582.219683,
      "lastTradePrice": 0.23
    },
    "will-russia-enter-zaporizhia-by-june-30-845": {
      "volumeNum": 67273.788117,
      "volume24hr": 3.31765,
      "lastTradePrice": 0.06
    },
    "will-russia-enter-sumy-by-june-30-893-434": {
      "volumeNum": 65926.62922800003,
      "volume24hr": 19.98,
      "lastTradePrice": 0.06
    },
    "will-russia-enter-ternuvate-again-by-march-31": {
      "volumeNum": 65770.12891000003,
      "volume24hr": 288.976816,
      "lastTradePrice": 0.12
    },
    "will-russia-capture-all-of-hryshyne-by": {
      "volumeNum": 64189.820919999926,
      "volume24hr": 11516.366448000002,
      "lastTradePrice": 0.996
    },
    "will-russia-enter-borova-by-march-31": {
      "volumeNum": 61897.58016100005,
      "volume24hr": 51.01,
      "lastTradePrice": 0.09
    },
    "will-russia-capture-rodynske-by-march-31": {
      "volumeNum": 58386.06643099999,
      "volume24hr": 2538.9015179999997,
      "lastTradePrice": 0.36
    },
    "will-russia-capture-bilytske-by-march-31-2026": {
      "volumeNum": 55322.98610400001,
      "volume24hr": 798.65,
      "lastTradePrice": 0.05
    },
    "will-russia-capture-lyman-by-april-30-2026": {
      "volumeNum": 51087.971611,
      "volume24hr": 433.986665,
      "lastTradePrice": 0.29
    },
    "will-russia-capture-havrylivka-by-april-30-2026": {
      "volumeNum": 50663.426396,
      "volume24hr": 2.9358940000000002,
      "lastTradePrice": 0.23
    },
    "will-russia-capture-all-of-donetsk-oblast-by-june-30-2026": {
      "volumeNum": 48198.635580000024,
      "volume24hr": 1194.497202,
      "lastTradePrice": 0.033
    },
    "will-russia-capture-hryshyne-by-april-30-2026-647-522": {
      "volumeNum": 44447.79787499999,
      "volume24hr": 9288.451330999998,
      "lastTradePrice": 0.998
    },
    "will-russia-enter-kherson-by-june-30-645": {
      "volumeNum": 41417.02119999999,
      "volume24hr": 349.58,
      "lastTradePrice": 0.046
    },
    "will-russia-capture-sofiivka-by-march-31": {
      "volumeNum": 38678.05303399999,
      "volume24hr": 436.931599,
      "lastTradePrice": 0.21
    },
    "will-ukraine-recapture-crimean-territory-by-june-30-2026": {
      "volumeNum": 38397.822683999984,
      "volume24hr": 179.062778,
      "lastTradePrice": 0.043
    },
    "will-russia-capture-kupiansk-vuzlovyi-by-march-31": {
      "volumeNum": 36914.10151799999,
      "volume24hr": 1509.594617,
      "lastTradePrice": 0.082
    },
    "will-russia-enter-kharkiv-by-june-30-967": {
      "volumeNum": 32343.173886000008,
      "volume24hr": 830.4053639999998,
      "lastTradePrice": 0.04
    },
    "will-russia-enter-verkhnia-tersa-by-march-31-2026": {
      "volumeNum": 30888.582954999998,
      "volume24hr": 2380.255,
      "lastTradePrice": 0.2
    },
    "will-ukraine-re-enter-uspenivka-by-march-31": {
      "volumeNum": 28895.368083999994,
      "volume24hr": 682.8153250000001,
      "lastTradePrice": 0.25
    },
    "will-russia-capture-all-of-drobysheve-by-march-31": {
      "volumeNum": 27138.786296000013,
      "volume24hr": 982.3590770000001,
      "lastTradePrice": 0.046
    },
    "will-russia-enter-vozdvyzhivka-by-march-31": {
      "volumeNum": 25908.09626500007,
      "volume24hr": 20.063290000000002,
      "lastTradePrice": 0.3
    },
    "will-russia-capture-toretske-by-march-31-2026": {
      "volumeNum": 23311.743791000034,
      "volume24hr": 292.11654599999997,
      "lastTradePrice": 0.22
    },
    "will-russia-enter-serhiivka-by-march-31": {
      "volumeNum": 22376.010901000016,
      "volume24hr": 165.66744,
      "lastTradePrice": 0.23
    },
    "will-russia-capture-lyman-by-june-30-2026-413": {
      "volumeNum": 22287.658980999993,
      "volume24hr": 1193.829694,
      "lastTradePrice": 0.69
    },
    "will-russia-capture-all-of-rodynske-by-april-30": {
      "volumeNum": 21983.831088000014,
      "volume24hr": 1011.2644779999999,
      "lastTradePrice": 0.7
    },
    "will-russia-enter-stinky-by-march-31": {
      "volumeNum": 20127.145160000007,
      "volume24hr": 3904.556553,
      "lastTradePrice": 0.22
    },
    "will-russia-capture-hryshyne-by-june-30-2026-484-168-415": {
      "volumeNum": 20007.041346000005,
      "volume24hr": 5530.6225,
      "lastTradePrice": 0.999
    },
    "will-russia-capture-all-of-lyman-by-june-30-2026": {
      "volumeNum": 17776.184893999998,
      "volume24hr": 31.80555,
      "lastTradePrice": 0.3
    },
    "will-russia-enter-orikhiv-by-june-30": {
      "volumeNum": 17487.490335,
      "volume24hr": 2560.7367559999993,
      "lastTradePrice": 0.28
    },
    "will-russia-capture-all-of-kupiansk-by-june-30": {
      "volumeNum": 15112.518538999997,
      "volume24hr": 138.225362,
      "lastTradePrice": 0.08
    },
    "will-russia-capture-all-of-kostyantynivka-by-june-30-2026": {
      "volumeNum": 13454.500774000007,
      "volume24hr": 410.756664,
      "lastTradePrice": 0.09
    },
    "will-russia-capture-all-of-kostyantynivka-by-december-31-2026": {
      "volumeNum": 13249.553560999993,
      "volume24hr": 31.59,
      "lastTradePrice": 0.6
    },
    "will-russia-capture-all-of-ternuvate-by-march-31-2026": {
      "volumeNum": 12422.964999000005,
      "volume24hr": 485.43,
      "lastTradePrice": 0.015
    },
    "will-russia-enter-novyi-donbas-by-march-31": {
      "volumeNum": 12258.434748,
      "volume24hr": 101.72176,
      "lastTradePrice": 0.17
    },
    "will-russia-capture-lyman-by-december-31-2026-774": {
      "volumeNum": 11275.254679000001,
      "volume24hr": 1087.080024,
      "lastTradePrice": 0.88
    },
    "will-russia-enter-rai-oleksandrivka-by-march-31-2026": {
      "volumeNum": 10822.091751,
      "volume24hr": 1427.552609,
      "lastTradePrice": 0.19
    },
    "will-russia-enter-dobropillia-by-march-31": {
      "volumeNum": 9357.578830999999,
      "volume24hr": 266.7,
      "lastTradePrice": 0.03
    },
    "will-russia-capture-all-of-stepnohirsk-by-april-30-2026": {
      "volumeNum": 7951.588353000009,
      "volume24hr": 427.822907,
      "lastTradePrice": 0.27
    },
    "will-ukraine-re-enter-obratne-or-temyrivka-by-march-31": {
      "volumeNum": 7644.311629999974,
      "volume24hr": 85.080464,
      "lastTradePrice": 0.22
    },
    "will-ukraine-re-enter-maliivka-by-march-31": {
      "volumeNum": 6198.820503999999,
      "volume24hr": 243.206665,
      "lastTradePrice": 0.12
    },
    "will-russia-enter-dobropillia-by-april-30": {
      "volumeNum": 4711.381257,
      "volume24hr": 111.659995,
      "lastTradePrice": 0.1
    },
    "will-russia-capture-pokrovka-by-march-31": {
      "volumeNum": 4217.551703,
      "volume24hr": 387.872994,
      "lastTradePrice": 0.31
    },
    "will-russia-capture-viroliubivka-by-march-31": {
      "volumeNum": 3923.8599139999983,
      "volume24hr": 70.706074,
      "lastTradePrice": 0.09
    },
    "will-russia-capture-all-of-prymorske-by-april-30-2026": {
      "volumeNum": 3637.363554,
      "volume24hr": 1.309266,
      "lastTradePrice": 0.19
    },
    "will-russia-enter-malokaterynivka-by-march-31-2026": {
      "volumeNum": 3218.0805090000003,
      "volume24hr": 2.486823,
      "lastTradePrice": 0.047
    },
    "will-russia-capture-rodynske-by-april-30": {
      "volumeNum": 3199.476534000001,
      "volume24hr": 864.0826139999999,
      "lastTradePrice": 0.67
    },
    "will-russia-enter-pokrovskoe-by-april-30-2026": {
      "volumeNum": 2826.713175000001,
      "volume24hr": 5.26,
      "lastTradePrice": 0.06
    },
    "will-russia-enter-dovha-balka-by-march-31": {
      "volumeNum": 2509.0113309999992,
      "volume24hr": 326.0687,
      "lastTradePrice": 0.23
    },
    "will-russia-enter-krasnopillya-by-april-30": {
      "volumeNum": 2508.0017970000004,
      "volume24hr": 1.136362,
      "lastTradePrice": 0.13
    },
    "will-russia-enter-shevchenko-by-march-31": {
      "volumeNum": 1848.4871070000002,
      "volume24hr": 147.396549,
      "lastTradePrice": 0.13
    },
    "will-russia-enter-svitle-by-march-31": {
      "volumeNum": 1281.262432,
      "volume24hr": 6.73,
      "lastTradePrice": 0.11
    },
    "will-russia-enter-kindrashivka-by-march-31": {
      "volumeNum": 820.4470739999996,
      "volume24hr": 49.41,
      "lastTradePrice": 0.14
    },
    "will-russia-capture-all-of-vovchansk-by-april-30": {
      "volumeNum": 648.4715690000002,
      "volume24hr": 14.999997,
      "lastTradePrice": 0.14
    },
    "will-russia-enter-krasnoiarske-by-march-31": {
      "volumeNum": 638.7172119999999,
      "volume24hr": 67.51,
      "lastTradePrice": 0.02
    },
    "will-russia-capture-bilytske-by-april-30-2026": {
      "volumeNum": 90,
      "volume24hr": 90,
      "lastTradePrice": 0.39
    },
    "will-russia-capture-sofiivka-by-april-30": {
      "volumeNum": 51.230587,
      "volume24hr": 51.230587,
      "lastTradePrice": 0.4
    },
    "will-russia-capture-all-of-huliaipole-by-april-30": {
      "volumeNum": 21.975651,
      "volume24hr": 21.975651,
      "lastTradePrice": 0.68
    },
    "will-russia-enter-novyi-donbas-by-april-30": {
      "volumeNum": 2.222221,
      "volume24hr": 2.222221,
      "lastTradePrice": 0.45
    },
    "will-russia-enter-khatnie-by-march-31-2026": {
      "volumeNum": 0,
      "volume24hr": 0,
      "lastTradePrice": 0.12
    },
    "will-russia-enter-havrylivka-by-march-31-2026": {
      "volumeNum": 0,
      "volume24hr": 0,
      "lastTradePrice": 0.05
    },
    "will-russia-enter-borova-by-april-30": {
      "volumeNum": 0,
      "volume24hr": 0,
      "lastTradePrice": 0.27
    },
    "will-russia-capture-havrylivka-by-march-31-2026": {
      "volumeNum": 0,
      "volume24hr": 0,
      "lastTradePrice": 0.05
    },
    "will-russia-enter-havrylivka-by-april-30-2026": {
      "volumeNum": 0,
      "volume24hr": 0,
      "lastTradePrice": 0.25
    },
    "will-russia-enter-khatnie-by-april-30-2026": {
      "volumeNum": 0,
      "volume24hr": 0,
      "lastTradePrice": 0
    },
    "will-russia-enter-malokaterynivka-by-april-30-2026": {
      "volumeNum": 0,
      "volume24hr": 0,
      "lastTradePrice": 0
    },
    "will-russia-capture-all-of-ternuvate-by-april-30-2026": {
      "volumeNum": 0,
      "volume24hr": 0,
      "lastTradePrice": 0
    },
    "will-russia-capture-all-of-drobysheve-by-april-30": {
      "volumeNum": 0,
      "volume24hr": 0,
      "lastTradePrice": 0
    },
    "will-russia-enter-svitle-by-april-30": {
      "volumeNum": 0,
      "volume24hr": 0,
      "lastTradePrice": 0
    },
    "will-russia-enter-shevchenko-by-april-30": {
      "volumeNum": 0,
      "volume24hr": 0,
      "lastTradePrice": 0
    },
    "will-russia-enter-kramatorsk-by-june-30-821-192": {
      "volumeNum": 0,
      "volume24hr": 0,
      "lastTradePrice": 0.17
    },
    "will-russia-capture-kindrativka-by-march-31": {
      "volumeNum": 0,
      "volume24hr": 0,
      "lastTradePrice": 0.09
    },
    "will-russia-enter-pokrovskoe-by-march-31-2026": {
      "volumeNum": 0,
      "volume24hr": 0,
      "lastTradePrice": 0.02
    },
    "russia-x-ukraine-ceasefire-by-march-31-2026": {
      "volumeNum": 24838871.652124368,
      "volume24hr": 157109.42954700004,
      "lastTradePrice": 0.02
    },
    "russia-x-ukraine-ceasefire-before-2027": {
      "volumeNum": 11619856.20909003,
      "volume24hr": 103651.45932099999,
      "lastTradePrice": 0.38
    },
    "russia-x-ukraine-ceasefire-by-june-30-2026": {
      "volumeNum": 3251861.2361980355,
      "volume24hr": 57368.99795600001,
      "lastTradePrice": 0.19
    },
    "putin-out-before-2027": {
      "volumeNum": 2730619.5705670104,
      "volume24hr": 52524.67767200001,
      "lastTradePrice": 0.12
    },
    "will-putin-meet-with-zelenskyy-by-march-31-2026": {
      "volumeNum": 2447601.7059749924,
      "volume24hr": 488.298777,
      "lastTradePrice": 0.008
    },
    "will-russia-invade-a-nato-country-by-june-30-2026": {
      "volumeNum": 2145596.143091002,
      "volume24hr": 279.122499,
      "lastTradePrice": 0.058
    },
    "zelenskyy-out-as-ukraine-president-before-2027": {
      "volumeNum": 1905527.5383090142,
      "volume24hr": 1572.594724,
      "lastTradePrice": 0.24
    },
    "will-russia-test-a-nuclear-weapon-by-march-31-2026": {
      "volumeNum": 1102055.6634150052,
      "volume24hr": 976.614243,
      "lastTradePrice": 0.014
    },
    "russia-strike-impacts-kyiv-municipality-during-week-of-march-2-2026": {
      "volumeNum": 1090807.725732,
      "volume24hr": 849105.6193770001,
      "lastTradePrice": 0.999
    },
    "putin-out-as-president-of-russia-by-june-30": {
      "volumeNum": 843499.0427149982,
      "volume24hr": 21508.542437,
      "lastTradePrice": 0.051
    },
    "russia-x-ukraine-ceasefire-by-april-30-2026": {
      "volumeNum": 584863.6442719995,
      "volume24hr": 18103.192403999998,
      "lastTradePrice": 0.06
    },
    "will-ukraine-agree-to-cede-territory-to-russia-before-2027": {
      "volumeNum": 505505.40193400136,
      "volume24hr": 1029.431023,
      "lastTradePrice": 0.25
    },
    "will-trump-and-putin-not-meet-315-857-437-514": {
      "volumeNum": 495233.6397440002,
      "volume24hr": 1140.1003719999999,
      "lastTradePrice": 0.646
    },
    "zelenskyy-out-as-ukraine-president-by-march-31-2026": {
      "volumeNum": 461748.13142299926,
      "volume24hr": 5322.230474000001,
      "lastTradePrice": 0.015
    },
    "nato-x-russia-military-clash-by-march-31-2026": {
      "volumeNum": 405043.7674339999,
      "volume24hr": 2110.1442839999995,
      "lastTradePrice": 0.028
    },
    "will-trump-and-putin-meet-next-in-another-european-country-954-837-364": {
      "volumeNum": 374184.622169,
      "volume24hr": 325520.92800400004,
      "lastTradePrice": 0.089
    },
    "russia-x-ukraine-peace-parlay": {
      "volumeNum": 362657.86003400024,
      "volume24hr": 623.421321,
      "lastTradePrice": 0.21
    },
    "ukraine-signs-peace-deal-with-russia-by-march-31": {
      "volumeNum": 314358.4433680006,
      "volume24hr": 7926.036596999999,
      "lastTradePrice": 0.029
    },
    "will-trump-and-putin-meet-next-in-russia-594-493-482": {
      "volumeNum": 285559.66419400007,
      "volume24hr": 137524.660671,
      "lastTradePrice": 0.038
    },
    "ukraine-election-called-by-march-31-2026": {
      "volumeNum": 234961.80493399946,
      "volume24hr": 1767.29,
      "lastTradePrice": 0.007
    },
    "will-the-us-test-a-nuclear-weapon-by-march-31-2026": {
      "volumeNum": 226722.07821499987,
      "volume24hr": 13114.875481999998,
      "lastTradePrice": 0.009
    },
    "ukraine-officially-agrees-to-a-us-backed-ceasefire-framework-by-march-31-214": {
      "volumeNum": 206294.02209000007,
      "volume24hr": 706.03,
      "lastTradePrice": 0.01
    },
    "ukraine-election-called-by-june-30-2026-392": {
      "volumeNum": 198162.42548700018,
      "volume24hr": 133.576863,
      "lastTradePrice": 0.1
    },
    "will-trump-meet-with-putin-by-march-31": {
      "volumeNum": 196603.58657600018,
      "volume24hr": 777.602136,
      "lastTradePrice": 0.028
    },
    "ukraine-election-held-by-june-30-2026-465-757": {
      "volumeNum": 194510.3965919999,
      "volume24hr": 44.256806999999995,
      "lastTradePrice": 0.07
    },
    "will-trump-and-putin-meet-next-in-belarus-572": {
      "volumeNum": 177229.30405199993,
      "volume24hr": 74442.634661,
      "lastTradePrice": 0.023
    },
    "ukraine-signs-peace-deal-with-russia-before-2027": {
      "volumeNum": 174637.10209099986,
      "volume24hr": 211.524206,
      "lastTradePrice": 0.28
    },
    "will-zelenskyy-talk-to-putin-by-march-31": {
      "volumeNum": 171481.4474240002,
      "volume24hr": 264.817445,
      "lastTradePrice": 0.021
    },
    "ukraine-recognizes-russian-sovereignty-over-its-territory-by-june-30-2026": {
      "volumeNum": 166733.3945300002,
      "volume24hr": 609.621828,
      "lastTradePrice": 0.063
    },
    "ukraine-election-held-by-december-31-2026-344-142": {
      "volumeNum": 166407.72652999996,
      "volume24hr": 170.28333199999997,
      "lastTradePrice": 0.2
    },
    "nato-x-russia-military-clash-by-june-30-2026": {
      "volumeNum": 164098.77949399993,
      "volume24hr": 9196.107971,
      "lastTradePrice": 0.128
    },
    "will-russia-capture-slovainsk-by-2027": {
      "volumeNum": 148262.68246899993,
      "volume24hr": 327.879504,
      "lastTradePrice": 0.09
    },
    "will-zelenskyy-and-putin-meet-next-in-belarus": {
      "volumeNum": 142418.03959899995,
      "volume24hr": 4383.93,
      "lastTradePrice": 0.004
    },
    "will-trump-and-putin-meet-next-in-china-586-328": {
      "volumeNum": 138892.73196700003,
      "volume24hr": 1465.972064,
      "lastTradePrice": 0.031
    },
    "will-putin-meet-with-zelenskyy-by-june-30-2026": {
      "volumeNum": 137355.963841,
      "volume24hr": 1180.189911,
      "lastTradePrice": 0.1
    },
    "will-trump-and-putin-meet-next-in-turkey-182-161-789": {
      "volumeNum": 128359.28265800003,
      "volume24hr": 2011.8047720000002,
      "lastTradePrice": 0.028
    },
    "will-us-withdraw-from-nato-before-2027": {
      "volumeNum": 127162.63497799994,
      "volume24hr": 1208.191394,
      "lastTradePrice": 0.038
    },
    "us-agrees-to-give-ukraine-security-guarantee-by-june-30": {
      "volumeNum": 121915.86186000003,
      "volume24hr": 741.918667,
      "lastTradePrice": 0.17
    },
    "will-trump-and-putin-meet-next-in-switzerland-448-348": {
      "volumeNum": 110408.72649000003,
      "volume24hr": 677.573137,
      "lastTradePrice": 0.024
    },
    "will-trump-and-putin-meet-next-in-ukraine-328-474": {
      "volumeNum": 109361.03997799999,
      "volume24hr": 852.27,
      "lastTradePrice": 0.004
    },
    "zelenskyy-out-as-ukraine-president-by-january-31-2026": {
      "volumeNum": 106341.0924,
      "volume24hr": 1.163594,
      "lastTradePrice": 0.11
    },
    "natoeu-troops-fighting-in-ukraine-in-june-30-2026": {
      "volumeNum": 92586.12263100012,
      "volume24hr": 477.989064,
      "lastTradePrice": 0.058
    },
    "european-country-agrees-to-give-ukraine-security-guarantee-by-june-30": {
      "volumeNum": 90031.24373199999,
      "volume24hr": 111.25,
      "lastTradePrice": 0.22
    },
    "ukraine-agrees-to-limit-size-of-armed-forces-before-2027": {
      "volumeNum": 80884.38701000006,
      "volume24hr": 33.791193,
      "lastTradePrice": 0.35
    },
    "will-zelenskyy-and-putin-not-meet": {
      "volumeNum": 74975.76199199996,
      "volume24hr": 930.5148,
      "lastTradePrice": 0.75
    },
    "will-trump-send-tomahawk-to-ukraine-by-march-31": {
      "volumeNum": 73916.87150100002,
      "volume24hr": 2968.868225,
      "lastTradePrice": 0.011
    },
    "will-trump-and-putin-meet-next-in-japan-711-288-527": {
      "volumeNum": 72749.520802,
      "volume24hr": 7123.393332,
      "lastTradePrice": 0.006
    },
    "will-trump-and-putin-meet-next-in-south-korea-582-297-268": {
      "volumeNum": 72191.02653999999,
      "volume24hr": 375.62999999999994,
      "lastTradePrice": 0.007
    },
    "will-trump-and-putin-meet-next-in-australia-459-332-211": {
      "volumeNum": 71263.618891,
      "volume24hr": 69.03,
      "lastTradePrice": 0.003
    },
    "eunato-country-announces-peacekeeping-force-in-ukraine-before-2027": {
      "volumeNum": 66636.14230399994,
      "volume24hr": 867.8366649999999,
      "lastTradePrice": 0.06
    },
    "will-zelenskyy-and-putin-meet-next-in-qatar-uae": {
      "volumeNum": 61697.010934,
      "volume24hr": 203.388063,
      "lastTradePrice": 0.026
    },
    "ukraine-agrees-not-to-join-nato-by-march-31": {
      "volumeNum": 59126.55979400007,
      "volume24hr": 274.797253,
      "lastTradePrice": 0.041
    },
    "ukraine-signs-peace-deal-with-russia-by-june-30": {
      "volumeNum": 58485.18649799991,
      "volume24hr": 41,
      "lastTradePrice": 0.14
    },
    "ukraine-agrees-not-to-join-nato-before-2027": {
      "volumeNum": 56015.53175199996,
      "volume24hr": 79.747807,
      "lastTradePrice": 0.27
    },
    "ukraine-peace-referendum-scheduled-by-june-30": {
      "volumeNum": 55370.502160999975,
      "volume24hr": 232.826085,
      "lastTradePrice": 0.23
    },
    "will-trump-and-putin-meet-next-in-finland-772-412": {
      "volumeNum": 53428.06782499973,
      "volume24hr": 4581.03,
      "lastTradePrice": 0.006
    },
    "will-zelenskyy-and-putin-meet-next-in-switzerland-848-193": {
      "volumeNum": 44934.18266100002,
      "volume24hr": 205.26,
      "lastTradePrice": 0.01
    },
    "will-trump-and-putin-meet-next-in-united-states-224-875-469": {
      "volumeNum": 41435.953652000004,
      "volume24hr": 235.433641,
      "lastTradePrice": 0.047
    },
    "will-trump-and-putin-meet-next-in-a-gulf-country-733-116": {
      "volumeNum": 40227.94776999997,
      "volume24hr": 312.411513,
      "lastTradePrice": 0.034
    },
    "will-zelenskyy-and-putin-meet-next-in-saudi-arabia": {
      "volumeNum": 36005.68086799999,
      "volume24hr": 77,
      "lastTradePrice": 0.015
    },
    "will-ukraine-agree-to-give-up-the-rest-of-donbas-before-2027": {
      "volumeNum": 33828.520799,
      "volume24hr": 3363.409511,
      "lastTradePrice": 0.16
    },
    "will-zelenskyy-and-putin-meet-next-in-turkey": {
      "volumeNum": 32887.5325,
      "volume24hr": 174.85,
      "lastTradePrice": 0.027
    },
    "will-zelenskyy-and-putin-meet-next-in-hungary": {
      "volumeNum": 30734.286128000083,
      "volume24hr": 66.67,
      "lastTradePrice": 0.026
    },
    "will-russia-strike-kyiv-on-march-31-2026": {
      "volumeNum": 26061.923211999998,
      "volume24hr": 1675.349721,
      "lastTradePrice": 0.114
    },
    "will-zelenskyy-and-putin-meet-next-in-italy-vatican": {
      "volumeNum": 25104.784798000004,
      "volume24hr": 181.82,
      "lastTradePrice": 0.006
    },
    "us-x-russia-nuclear-deal-by-june-30": {
      "volumeNum": 23359.622768000023,
      "volume24hr": 71.397332,
      "lastTradePrice": 0.15
    },
    "will-trump-and-putin-meet-next-in-another-country-313-781-734-447": {
      "volumeNum": 23058.069794,
      "volume24hr": 126.649046,
      "lastTradePrice": 0.017
    },
    "ukraine-officially-agrees-to-a-us-backed-ceasefire-framework-by-june-30": {
      "volumeNum": 17404.706687999984,
      "volume24hr": 23.715135,
      "lastTradePrice": 0.14
    },
    "ukraine-peace-referendum-scheduled-by-march-31": {
      "volumeNum": 13905.650731999998,
      "volume24hr": 31.84,
      "lastTradePrice": 0.024
    },
    "russia-strike-impacts-kyiv-municipality-during-week-of-march-9-2026": {
      "volumeNum": 13235.698220999999,
      "volume24hr": 8810.215398,
      "lastTradePrice": 0.37
    },
    "nato-x-russia-military-clash-by-december-31-2026-244": {
      "volumeNum": 11499.869087000001,
      "volume24hr": 478.178568,
      "lastTradePrice": 0.24
    },
    "will-russia-rejoin-the-g7-before-2027": {
      "volumeNum": 8127.428159000002,
      "volume24hr": 229.09016200000002,
      "lastTradePrice": 0.189
    },
    "trump-putin-and-zelensky-seen-together-before-2027": {
      "volumeNum": 6835.938866999998,
      "volume24hr": 2.63,
      "lastTradePrice": 0.14
    },
    "more-eu-sanctions-on-russia-by-march-31": {
      "volumeNum": 4308.431866,
      "volume24hr": 224.333156,
      "lastTradePrice": 0.25
    },
    "putin-and-zelenskyy-shake-hands-by-june-30": {
      "volumeNum": 4163.954508000001,
      "volume24hr": 16.753165,
      "lastTradePrice": 0.06
    },
    "will-zelenskyy-talk-to-putin-by-december-31-992": {
      "volumeNum": 3664.5035110000003,
      "volume24hr": 139.480131,
      "lastTradePrice": 0.28
    },
    "nord-stream-pipeline-turned-on-before-2027": {
      "volumeNum": 3484.0176569999994,
      "volume24hr": 604.224721,
      "lastTradePrice": 0.11
    },
    "ukraine-hits-moscow-by-march-31-2026": {
      "volumeNum": 2830.1448719999994,
      "volume24hr": 176.677736,
      "lastTradePrice": 0.11
    },
    "ukraine-strikes-another-tanker-in-black-sea-by-march-31-2026": {
      "volumeNum": 961.1935910000002,
      "volume24hr": 178.059408,
      "lastTradePrice": 0.17
    },
    "russia-x-ukraine-ceasefire-before-us-x-iran-ceasefire": {
      "volumeNum": 360.650511,
      "volume24hr": 360.650511,
      "lastTradePrice": 0.22
    },
    "trump-putin-and-zelensky-meet-together-before-2027": {
      "volumeNum": 0,
      "volume24hr": 0,
      "lastTradePrice": 0.24
    },
    "will-zelenskyy-and-putin-meet-next-in-russia": {
      "volumeNum": 0,
      "volume24hr": 0,
      "lastTradePrice": 0.013
    },
    "ukraine-recognizes-russian-sovereignty-over-its-territory-by-december-31-2026": {
      "volumeNum": 0,
      "volume24hr": 0,
      "lastTradePrice": 0.15
    },
    "ukraine-joins-nato-before-2027": {
      "volumeNum": 0,
      "volume24hr": 0,
      "lastTradePrice": 0.032
    },
    "will-zelenskyy-and-putin-meet-next-in-ukraine": {
      "volumeNum": 0,
      "volume24hr": 0,
      "lastTradePrice": 0.005
    },
    "eunato-country-announces-peacekeeping-force-in-ukraine-by-december-31": {
      "volumeNum": 0,
      "volume24hr": 0,
      "lastTradePrice": 0.29
    },
    "ukraine-coup-attempt-by-june-30": {
      "volumeNum": 0,
      "volume24hr": 0,
      "lastTradePrice": 0.08
    },
    "will-zelenskyy-and-putin-meet-next-in-china": {
      "volumeNum": 0,
      "volume24hr": 0,
      "lastTradePrice": 0.006
    },
    "will-zelenskyy-and-putin-meet-next-in-us": {
      "volumeNum": 0,
      "volume24hr": 0,
      "lastTradePrice": 0.024
    },
    "will-zelenskyy-and-putin-meet-next-in-india-416-286": {
      "volumeNum": 0,
      "volume24hr": 0,
      "lastTradePrice": 0.005
    },
    "will-zelenskyy-and-putin-meet-next-in-kazakhstan-485-344": {
      "volumeNum": 0,
      "volume24hr": 0,
      "lastTradePrice": 0.004
    },
    "ukraine-peace-referendum-passed-by-december-31-2026": {
      "volumeNum": 0,
      "volume24hr": 0,
      "lastTradePrice": 0.28
    },
    "will-a-us-ally-get-a-nuke-before-2027": {
      "volumeNum": 0,
      "volume24hr": 0,
      "lastTradePrice": 0.16
    },
    "us-recognizes-russian-sovereignty-over-ukraine-before-2027": {
      "volumeNum": 0,
      "volume24hr": 0,
      "lastTradePrice": 0.27
    },
    "ukraine-agrees-not-to-join-nato-by-june-30": {
      "volumeNum": 0,
      "volume24hr": 0,
      "lastTradePrice": 0.16
    },
    "will-donald-trump-win-the-nobel-peace-prize-in-2026-382": {
      "volumeNum": 2112842.83981199,
      "volume24hr": 5320.030361,
      "lastTradePrice": 0.08
    },
    "will-unrwa-win-the-nobel-peace-prize-in-2026-983": {
      "volumeNum": 1433890.6720060036,
      "volume24hr": 7021.410037000002,
      "lastTradePrice": 0.028
    },
    "russia-ukraine-ceasefire-before-gta-vi-554": {
      "volumeNum": 1370422.2289739999,
      "volume24hr": 1680.6202869999997,
      "lastTradePrice": 0.58
    },
    "will-greta-thunberg-win-the-nobel-peace-prize-in-2026-767": {
      "volumeNum": 800896.4536909973,
      "volume24hr": 8482.829999999998,
      "lastTradePrice": 0.023
    },
    "will-xi-jinping-win-the-nobel-peace-prize-in-2026": {
      "volumeNum": 539311.446099,
      "volume24hr": 126547.82080500001,
      "lastTradePrice": 0.006
    },
    "will-ukraine-win-eurovision-2026": {
      "volumeNum": 477653.72364999854,
      "volume24hr": 27104.221050999993,
      "lastTradePrice": 0.023
    },
    "will-elon-musk-win-the-nobel-peace-prize-in-2026-756": {
      "volumeNum": 461677.87696199847,
      "volume24hr": 5440.999502,
      "lastTradePrice": 0.021
    },
    "will-ahmed-al-sharaa-win-the-nobel-peace-prize-in-2026": {
      "volumeNum": 453553.7578219999,
      "volume24hr": 1597.1824000000004,
      "lastTradePrice": 0.01
    },
    "will-vladimir-putin-win-the-nobel-peace-prize-in-2026-126": {
      "volumeNum": 371175.7149780001,
      "volume24hr": 34.190599999999996,
      "lastTradePrice": 0.006
    },
    "will-volodymyr-zelensky-win-the-nobel-peace-prize-in-2026-637": {
      "volumeNum": 332471.8486289997,
      "volume24hr": 652.086616,
      "lastTradePrice": 0.127
    },
    "will-charlie-kirk-win-the-nobel-peace-prize-in-2026": {
      "volumeNum": 324355.2923939999,
      "volume24hr": 8241.5795,
      "lastTradePrice": 0.023
    },
    "will-julian-assange-win-the-nobel-peace-prize-in-2026-899": {
      "volumeNum": 259296.0003579999,
      "volume24hr": 745.63,
      "lastTradePrice": 0.01
    },
    "will-mohammed-bin-salman-win-the-nobel-peace-prize-in-2026": {
      "volumeNum": 258672.069076,
      "volume24hr": 1156.4940940000001,
      "lastTradePrice": 0.007
    },
    "will-recep-tayyip-erdoan-win-the-nobel-peace-prize-in-2026": {
      "volumeNum": 249000.27706899992,
      "volume24hr": 4614.486629,
      "lastTradePrice": 0.01
    },
    "will-benjamin-netanyahu-win-the-nobel-peace-prize-in-2026": {
      "volumeNum": 233321.96368700004,
      "volume24hr": 2401.34,
      "lastTradePrice": 0.007
    },
    "will-narendra-modi-win-the-nobel-peace-prize-in-2026": {
      "volumeNum": 223580.04598600024,
      "volume24hr": 4295.429128999998,
      "lastTradePrice": 0.02
    },
    "will-pope-leo-xiv-win-the-nobel-peace-prize-in-2026-698": {
      "volumeNum": 160646.15844499995,
      "volume24hr": 4332.657141,
      "lastTradePrice": 0.056
    },
    "will-tamim-bin-hamad-al-thani-win-the-nobel-peace-prize-in-2026-755": {
      "volumeNum": 147837.442857,
      "volume24hr": 419.15,
      "lastTradePrice": 0.043
    },
    "will-the-international-court-of-justice-win-the-nobel-peace-prize-in-2026-885": {
      "volumeNum": 143099.79139199984,
      "volume24hr": 1934.749361,
      "lastTradePrice": 0.032
    },
    "will-ukraine-qualify-for-the-2026-fifa-world-cup": {
      "volumeNum": 139191.53553100018,
      "volume24hr": 274.527721,
      "lastTradePrice": 0.3
    },
    "will-khaled-mashal-win-the-nobel-peace-prize-in-2026-787": {
      "volumeNum": 91770.836413,
      "volume24hr": 762.0539,
      "lastTradePrice": 0.006
    },
    "will-antnio-guterres-win-the-nobel-peace-prize-in-2026-623": {
      "volumeNum": 91615.05872000003,
      "volume24hr": 1066.794614,
      "lastTradePrice": 0.013
    }
  }
}