{
  "timestamp": "2026-04-27T06:40:29.338272+00:00",
  "markets": {
    "will-russia-capture-kostyantynivka-by-december-31-2026-936-942-271-276-578-687": {
      "volumeNum": 357974.25966800016,
      "volume24hr": 3199.992528,
      "lastTradePrice": 0.8
    },
    "will-russia-capture-sumy-by-march-31-2027": {
      "volumeNum": 280911.93001400674,
      "volume24hr": 1229.04,
      "lastTradePrice": 0.18
    },
    "will-russia-enter-druzkhivka-by-june-30-933-897": {
      "volumeNum": 275682.0339090001,
      "volume24hr": 208.26,
      "lastTradePrice": 0.07
    },
    "will-russia-capture-kostyantynivka-by-june-30-382-954-769": {
      "volumeNum": 218561.93038199973,
      "volume24hr": 518.89918,
      "lastTradePrice": 0.45
    },
    "will-russia-capture-lyman-by-april-30-2026": {
      "volumeNum": 194578.4135510002,
      "volume24hr": 1285.83521,
      "lastTradePrice": 0.019
    },
    "will-russia-enter-dopropillia-by-june-30-122-495": {
      "volumeNum": 194394.83697000178,
      "volume24hr": 7.609188,
      "lastTradePrice": 0.27
    },
    "will-russia-capture-kostyantynivka-by-april-30": {
      "volumeNum": 180492.6886389999,
      "volume24hr": 2070.497391,
      "lastTradePrice": 0.041
    },
    "will-russia-capture-all-of-prymorske-by-april-30-2026": {
      "volumeNum": 169672.79635600012,
      "volume24hr": 77.88766000000001,
      "lastTradePrice": 0.005
    },
    "will-russia-capture-lyman-by-june-30-2026-413": {
      "volumeNum": 162523.35188799893,
      "volume24hr": 4106.471258,
      "lastTradePrice": 0.2
    },
    "will-russia-enter-sloviansk-by-june-30": {
      "volumeNum": 156634.39844099997,
      "volume24hr": 207.24,
      "lastTradePrice": 0.08
    },
    "will-russia-capture-all-of-huliaipole-by-april-30": {
      "volumeNum": 153485.5141739997,
      "volume24hr": 8649.027119999999,
      "lastTradePrice": 0.06
    },
    "will-russia-capture-all-of-lyman-by-december-31-2026": {
      "volumeNum": 135899.47867899996,
      "volume24hr": 367.936506,
      "lastTradePrice": 0.39
    },
    "will-russia-enter-kramatorsk-by-june-30-821-192": {
      "volumeNum": 134416.0464420001,
      "volume24hr": 3.92,
      "lastTradePrice": 0.05
    },
    "will-russia-enter-mykhailivka-by-april-30": {
      "volumeNum": 89026.7095550001,
      "volume24hr": 17.5,
      "lastTradePrice": 0.029
    },
    "will-russia-capture-lyman-by-december-31-2026-774": {
      "volumeNum": 88587.27180500004,
      "volume24hr": 761.67487,
      "lastTradePrice": 0.65
    },
    "will-russia-capture-all-of-donetsk-oblast-by-june-30-2026": {
      "volumeNum": 87334.69532399997,
      "volume24hr": 747.667753,
      "lastTradePrice": 0.028
    },
    "will-russia-capture-all-of-kostyantynivka-by-december-31-2026": {
      "volumeNum": 82093.32908499999,
      "volume24hr": 15956.168045999999,
      "lastTradePrice": 0.34
    },
    "will-russia-enter-zaporizhia-by-june-30-845": {
      "volumeNum": 77047.75666700001,
      "volume24hr": 0,
      "lastTradePrice": 0.04
    },
    "will-russia-capture-all-of-kostyantynivka-by-june-30-2026": {
      "volumeNum": 75017.35538899993,
      "volume24hr": 2056.599848,
      "lastTradePrice": 0.057
    },
    "will-russia-capture-bilytske-by-april-30-2026": {
      "volumeNum": 74883.2296770002,
      "volume24hr": 371.1618680000001,
      "lastTradePrice": 0.04
    },
    "will-russia-enter-sumy-by-june-30-893-434": {
      "volumeNum": 74436.06321700003,
      "volume24hr": 540,
      "lastTradePrice": 0.05
    },
    "will-ukraine-recapture-crimean-territory-by-june-30-2026": {
      "volumeNum": 64046.02428399994,
      "volume24hr": 328.17351199999996,
      "lastTradePrice": 0.029
    },
    "will-russia-enter-kherson-by-june-30-645": {
      "volumeNum": 59916.56961199997,
      "volume24hr": 910.972443,
      "lastTradePrice": 0.034
    },
    "will-russia-enter-novooleksandrivka-by-april-30-2026": {
      "volumeNum": 59106.02986000011,
      "volume24hr": 1521.4041759999998,
      "lastTradePrice": 0.18
    },
    "will-russia-capture-havrylivka-by-april-30-2026": {
      "volumeNum": 53132.904886000026,
      "volume24hr": 207.83,
      "lastTradePrice": 0.01
    },
    "will-russia-enter-novyi-donbas-by-april-30": {
      "volumeNum": 52906.18613600003,
      "volume24hr": 7286.904686000001,
      "lastTradePrice": 0.14
    },
    "will-russia-enter-orikhiv-by-june-30": {
      "volumeNum": 50514.967358000016,
      "volume24hr": 129.964742,
      "lastTradePrice": 0.2
    },
    "will-russia-capture-all-of-drobysheve-by-april-30": {
      "volumeNum": 44819.693401,
      "volume24hr": 1420.56,
      "lastTradePrice": 0.004
    },
    "will-russia-enter-ternuvate-again-by-april-30": {
      "volumeNum": 43190.07236600013,
      "volume24hr": 887.1532399999999,
      "lastTradePrice": 0.14
    },
    "will-russia-capture-all-of-kupiansk-by-june-30": {
      "volumeNum": 41574.016428999974,
      "volume24hr": 4148.443297000001,
      "lastTradePrice": 0.05
    },
    "will-russia-capture-all-of-hryshyne-by-april-30": {
      "volumeNum": 40933.36569100002,
      "volume24hr": 2322.8713209999987,
      "lastTradePrice": 0.1
    },
    "will-russia-capture-all-of-stepnohirsk-by-april-30-2026": {
      "volumeNum": 37799.06672900003,
      "volume24hr": 1,
      "lastTradePrice": 0.02
    },
    "will-russia-enter-kharkiv-by-june-30-967": {
      "volumeNum": 37355.20314700001,
      "volume24hr": 458.41,
      "lastTradePrice": 0.041
    },
    "will-russia-enter-vozdvyzhivka-by-april-30": {
      "volumeNum": 34760.39925100001,
      "volume24hr": 1168.761564,
      "lastTradePrice": 0.11
    },
    "will-russia-enter-vasylivka-by-april-30-2026": {
      "volumeNum": 33105.32915500001,
      "volume24hr": 1107.2000000000003,
      "lastTradePrice": 0.1
    },
    "will-russia-capture-all-of-lyman-by-june-30-2026": {
      "volumeNum": 30952.02805199997,
      "volume24hr": 0,
      "lastTradePrice": 0.1
    },
    "will-ukraine-re-enter-maliivka-by-april-30": {
      "volumeNum": 29543.486932999993,
      "volume24hr": 855.3029190000001,
      "lastTradePrice": 0.05
    },
    "will-russia-capture-sofiivka-by-april-30": {
      "volumeNum": 29151.042182999983,
      "volume24hr": 87.879833,
      "lastTradePrice": 0.033
    },
    "will-russia-enter-shevchenko-by-april-30": {
      "volumeNum": 21018.703823000007,
      "volume24hr": 934.371445,
      "lastTradePrice": 0.05
    },
    "will-russia-capture-all-of-ternuvate-by-april-30-2026": {
      "volumeNum": 19090.156686999988,
      "volume24hr": 153.815186,
      "lastTradePrice": 0.012
    },
    "will-russia-capture-all-of-bilytske-by-june-30": {
      "volumeNum": 18985.986602999998,
      "volume24hr": 886.568155,
      "lastTradePrice": 0.13
    },
    "will-russia-enter-svitle-by-april-30": {
      "volumeNum": 14648.024609999995,
      "volume24hr": 262.260553,
      "lastTradePrice": 0.047
    },
    "will-russia-capture-all-of-pokrovsk-by-april-30-2026": {
      "volumeNum": 13830.037517999997,
      "volume24hr": 97.644686,
      "lastTradePrice": 0.06
    },
    "will-russia-capture-all-of-vovchansk-by-april-30": {
      "volumeNum": 13283.933056999995,
      "volume24hr": 54.193211999999995,
      "lastTradePrice": 0.04
    },
    "will-ukraine-re-enter-uspenivka-by-april-30": {
      "volumeNum": 13164.682940999997,
      "volume24hr": 308.679,
      "lastTradePrice": 0.028
    },
    "will-russia-enter-dobropillia-by-april-30": {
      "volumeNum": 12593.934095999997,
      "volume24hr": 148.307976,
      "lastTradePrice": 0.017
    },
    "will-russia-capture-pokrovka-by-april-30": {
      "volumeNum": 11258.24805400001,
      "volume24hr": 591.530171,
      "lastTradePrice": 0.06
    },
    "will-russia-enter-stinky-by-april-30": {
      "volumeNum": 11198.500657999997,
      "volume24hr": 6.018391,
      "lastTradePrice": 0.026
    },
    "will-russia-enter-pokrovskoe-by-april-30-2026": {
      "volumeNum": 10162.092311,
      "volume24hr": 41,
      "lastTradePrice": 0.01
    },
    "will-russia-enter-huliaipilske-by-april-30": {
      "volumeNum": 9011.884031,
      "volume24hr": 267.557638,
      "lastTradePrice": 0.1
    },
    "will-russia-capture-all-of-pokrovsk-by-may-31-2026": {
      "volumeNum": 8839.208627999997,
      "volume24hr": 765.25058,
      "lastTradePrice": 0.36
    },
    "will-russia-enter-novyi-donbas-by-may-31": {
      "volumeNum": 7648.456188,
      "volume24hr": 1159.362553,
      "lastTradePrice": 0.7
    },
    "will-ukraine-re-enter-obratne-or-temyrivka-by-april-30": {
      "volumeNum": 6877.138642000003,
      "volume24hr": 464.146961,
      "lastTradePrice": 0.033
    },
    "will-russia-capture-all-of-huliaipole-by-may-31": {
      "volumeNum": 5987.3985689999945,
      "volume24hr": 2137.8981909999984,
      "lastTradePrice": 0.37
    },
    "will-russia-capture-viroliubivka-by-april-30": {
      "volumeNum": 5803.283895999998,
      "volume24hr": 202.088333,
      "lastTradePrice": 0.013
    },
    "will-russia-enter-khatnie-by-april-30-2026": {
      "volumeNum": 5665.707210000001,
      "volume24hr": 0,
      "lastTradePrice": 0.01
    },
    "will-russia-capture-kostyantynivka-by-may-31": {
      "volumeNum": 5563.777697999999,
      "volume24hr": 1175.614101,
      "lastTradePrice": 0.28
    },
    "will-ukraine-re-enter-uspenivka-by-may-31": {
      "volumeNum": 5463.15651899999,
      "volume24hr": 97,
      "lastTradePrice": 0.13
    },
    "will-russia-capture-serhiivka-by-april-30": {
      "volumeNum": 5420.369027000001,
      "volume24hr": 232.131842,
      "lastTradePrice": 0.022
    },
    "will-russia-capture-kupiansk-vuzlovyi-by-april-30": {
      "volumeNum": 5357.403495999998,
      "volume24hr": 268.779854,
      "lastTradePrice": 0.032
    },
    "will-russia-enter-krasnopillya-by-april-30": {
      "volumeNum": 5264.007152999999,
      "volume24hr": 100.6,
      "lastTradePrice": 0.05
    },
    "will-russia-enter-serhiivka-by-april-30": {
      "volumeNum": 5174.469896000001,
      "volume24hr": 285.02862700000003,
      "lastTradePrice": 0.033
    },
    "will-russia-capture-huliaipilske-by-may-31": {
      "volumeNum": 4924.502978,
      "volume24hr": 0,
      "lastTradePrice": 0.1
    },
    "will-russia-capture-dovha-balka-by-april-30": {
      "volumeNum": 4780.234500000001,
      "volume24hr": 443.934717,
      "lastTradePrice": 0.059
    },
    "will-russia-enter-kindrashivka-by-april-30": {
      "volumeNum": 4726.421413999999,
      "volume24hr": 508.78999999999996,
      "lastTradePrice": 0.038
    },
    "will-russia-enter-moskovka-by-may-31": {
      "volumeNum": 4519.454943000022,
      "volume24hr": 626.5811749999999,
      "lastTradePrice": 0.27
    },
    "will-ukraine-re-enter-myrnohrad-by-may-31": {
      "volumeNum": 3381.508099999999,
      "volume24hr": 393.12427400000007,
      "lastTradePrice": 0.16
    },
    "will-russia-enter-huliaipilske-by-may-31": {
      "volumeNum": 3340.875228000001,
      "volume24hr": 180.546474,
      "lastTradePrice": 0.66
    },
    "will-russia-enter-borova-by-april-30": {
      "volumeNum": 3110.301675,
      "volume24hr": 163.51,
      "lastTradePrice": 0.05
    },
    "will-russia-enter-moskovka-by-april-30": {
      "volumeNum": 2890.19994,
      "volume24hr": 0,
      "lastTradePrice": 0.039
    },
    "will-russia-capture-kindrativka-by-april-30": {
      "volumeNum": 2832.507036,
      "volume24hr": 26.737966,
      "lastTradePrice": 0.187
    },
    "will-russia-capture-dovha-balka-by-may-31": {
      "volumeNum": 2770.4964289999953,
      "volume24hr": 2309.8645280000005,
      "lastTradePrice": 0.26
    },
    "will-russia-enter-malokaterynivka-by-april-30-2026": {
      "volumeNum": 2576.692237999999,
      "volume24hr": 0,
      "lastTradePrice": 0.03
    },
    "will-russia-enter-myrne-by-april-30-2026": {
      "volumeNum": 2450.7624999999994,
      "volume24hr": 47.81052,
      "lastTradePrice": 0.05
    },
    "will-russia-enter-riasne-by-may-31": {
      "volumeNum": 2396.345168999978,
      "volume24hr": 134.710283,
      "lastTradePrice": 0.25
    },
    "will-russia-capture-bilytske-by-may-31-2026": {
      "volumeNum": 2380.0994099999834,
      "volume24hr": 923.5776069999997,
      "lastTradePrice": 0.24
    },
    "will-russia-enter-havrylivka-by-april-30-2026": {
      "volumeNum": 2294.8242480000004,
      "volume24hr": 122.61254100000001,
      "lastTradePrice": 0.038
    },
    "will-russia-enter-novooleksandrivka-by-may-31-2026": {
      "volumeNum": 2243.2931780000004,
      "volume24hr": 591.635595,
      "lastTradePrice": 0.78
    },
    "will-russia-capture-toretske-by-april-30-2026": {
      "volumeNum": 1924.2189289999997,
      "volume24hr": 373.072591,
      "lastTradePrice": 0.054
    },
    "will-russia-capture-all-of-hryshyne-by-may-31": {
      "volumeNum": 1617.5640490000003,
      "volume24hr": 674.809822,
      "lastTradePrice": 0.5
    },
    "will-russia-capture-verkhnia-tersa-by-may-31": {
      "volumeNum": 1432.0703389999999,
      "volume24hr": 19.232657,
      "lastTradePrice": 0.24
    },
    "will-russia-capture-all-of-prymorske-by-may-31-2026": {
      "volumeNum": 1254.981502,
      "volume24hr": 56.390975,
      "lastTradePrice": 0.07
    },
    "will-russia-enter-vozdvyzhivka-by-may-31": {
      "volumeNum": 1233.9074480000002,
      "volume24hr": 286.47666300000003,
      "lastTradePrice": 0.36
    },
    "will-russia-enter-krasnoiarske-by-april-30": {
      "volumeNum": 1049.6308239999998,
      "volume24hr": 174.85818,
      "lastTradePrice": 0.033
    },
    "will-russia-capture-lyman-by-may-31-2026": {
      "volumeNum": 773.152215,
      "volume24hr": 733.15555,
      "lastTradePrice": 0.1
    },
    "will-russia-capture-huliaipilske-by-april-30": {
      "volumeNum": 746.9752809999997,
      "volume24hr": 4.831789,
      "lastTradePrice": 0.047
    },
    "will-russia-enter-ternuvate-again-by-may-31": {
      "volumeNum": 702.9494169999999,
      "volume24hr": 179.105532,
      "lastTradePrice": 0.53
    },
    "will-russia-capture-kindrativka-by-may-31": {
      "volumeNum": 644.8232009999999,
      "volume24hr": 48.91,
      "lastTradePrice": 0.35
    },
    "will-russia-enter-orikhiv-by-may-31": {
      "volumeNum": 520.8199999999999,
      "volume24hr": 0,
      "lastTradePrice": 0.17
    },
    "will-russia-capture-kupiansk-vuzlovyi-by-may-31": {
      "volumeNum": 518.4928170000001,
      "volume24hr": 25.02,
      "lastTradePrice": 0.11
    },
    "will-russia-enter-shevchenko-by-may-31": {
      "volumeNum": 471.6078880000001,
      "volume24hr": 112.35706,
      "lastTradePrice": 0.57
    },
    "will-russia-capture-all-of-ternuvate-by-may-31-2026": {
      "volumeNum": 467.112236,
      "volume24hr": 15.9,
      "lastTradePrice": 0.06
    },
    "will-russia-capture-toretske-by-may-31-2026": {
      "volumeNum": 379,
      "volume24hr": 49,
      "lastTradePrice": 0.26
    },
    "will-russia-capture-all-of-drobysheve-by-may-31": {
      "volumeNum": 367.691245,
      "volume24hr": 0,
      "lastTradePrice": 0.02
    },
    "will-russia-capture-myropillia-by-may-31": {
      "volumeNum": 325.50344500000006,
      "volume24hr": 0,
      "lastTradePrice": 0.09
    },
    "will-russia-capture-all-of-vovchansk-by-may-31": {
      "volumeNum": 305,
      "volume24hr": 55,
      "lastTradePrice": 0.09
    },
    "will-russia-enter-vasylivka-by-may-31-2026": {
      "volumeNum": 266.09336299999995,
      "volume24hr": 0,
      "lastTradePrice": 0.26
    },
    "will-russia-enter-malokaterynivka-by-may-31-2026": {
      "volumeNum": 255.82444600000002,
      "volume24hr": 26.429766,
      "lastTradePrice": 0.021
    },
    "will-russia-enter-borova-by-may-31": {
      "volumeNum": 247.083332,
      "volume24hr": 0,
      "lastTradePrice": 0.23
    },
    "will-russia-capture-riasne-by-may-31": {
      "volumeNum": 240.39024899999995,
      "volume24hr": 0,
      "lastTradePrice": 0.08
    },
    "will-russia-enter-svitle-by-may-31": {
      "volumeNum": 219.053702,
      "volume24hr": 219.05370200000002,
      "lastTradePrice": 0.41
    },
    "will-russia-enter-khatnie-by-may-31-2026": {
      "volumeNum": 213.67,
      "volume24hr": 0,
      "lastTradePrice": 0.15
    },
    "will-russia-enter-pokrovskoe-by-may-31-2026": {
      "volumeNum": 199.37166699999997,
      "volume24hr": 0,
      "lastTradePrice": 0
    },
    "will-russia-capture-havrylivka-by-may-31-2026": {
      "volumeNum": 187.031272,
      "volume24hr": 187.031272,
      "lastTradePrice": 0
    },
    "will-russia-enter-myrne-by-may-31-2026": {
      "volumeNum": 136.103895,
      "volume24hr": 31.103895,
      "lastTradePrice": 0.4
    },
    "will-russia-enter-krasnoiarske-by-may-31": {
      "volumeNum": 97.32262,
      "volume24hr": 50,
      "lastTradePrice": 0
    },
    "will-ukraine-re-enter-maliivka-by-may-31": {
      "volumeNum": 93.238843,
      "volume24hr": 6.976743,
      "lastTradePrice": 0.43
    },
    "will-russia-capture-serhiivka-by-may-31": {
      "volumeNum": 61.6,
      "volume24hr": 0,
      "lastTradePrice": 0
    },
    "will-russia-capture-viroliubivka-by-may-31": {
      "volumeNum": 55.190475,
      "volume24hr": 0,
      "lastTradePrice": 0.16
    },
    "will-russia-enter-stinky-by-may-31": {
      "volumeNum": 54.539997,
      "volume24hr": 49.994544,
      "lastTradePrice": 0.22
    },
    "will-russia-enter-mykhailivka-by-may-31": {
      "volumeNum": 53.268283,
      "volume24hr": 32,
      "lastTradePrice": 0
    },
    "will-ukraine-re-enter-obratne-or-temyrivka-by-may-31": {
      "volumeNum": 37.436287,
      "volume24hr": 0,
      "lastTradePrice": 0.47
    },
    "will-russia-capture-all-of-stepnohirsk-by-may-31-2026": {
      "volumeNum": 26.98888,
      "volume24hr": 1.98888,
      "lastTradePrice": 0.12
    },
    "will-russia-enter-havrylivka-by-may-31-2026": {
      "volumeNum": 10.606058,
      "volume24hr": 8.333332,
      "lastTradePrice": 0.44
    },
    "will-russia-capture-sofiivka-by-may-31": {
      "volumeNum": 9.615383,
      "volume24hr": 9.615383,
      "lastTradePrice": 0.35
    },
    "will-russia-enter-kindrashivka-by-may-31": {
      "volumeNum": 8.333332,
      "volume24hr": 8.333332,
      "lastTradePrice": 0
    },
    "will-russia-enter-krasnopillya-by-may-31": {
      "volumeNum": 8.333332,
      "volume24hr": 8.333332,
      "lastTradePrice": 0
    },
    "will-russia-capture-pokrovka-by-may-31": {
      "volumeNum": 8.333332,
      "volume24hr": 0,
      "lastTradePrice": 0
    },
    "will-russia-enter-serhiivka-by-may-31": {
      "volumeNum": 0,
      "volume24hr": 0,
      "lastTradePrice": 0
    },
    "will-russia-enter-orikhiv-by-july-31": {
      "volumeNum": 0,
      "volume24hr": 0,
      "lastTradePrice": 0
    },
    "will-russia-enter-dobropillia-by-may-31": {
      "volumeNum": 0,
      "volume24hr": 0,
      "lastTradePrice": 0
    },
    "russia-x-ukraine-ceasefire-before-2027": {
      "volumeNum": 14502613.985482976,
      "volume24hr": 49029.688754999996,
      "lastTradePrice": 0.26
    },
    "russia-x-ukraine-ceasefire-by-april-30-2026": {
      "volumeNum": 8792375.024811883,
      "volume24hr": 665370.3242640003,
      "lastTradePrice": 0.002
    },
    "russia-x-ukraine-ceasefire-by-june-30-2026": {
      "volumeNum": 6637919.6755980365,
      "volume24hr": 53063.01281399999,
      "lastTradePrice": 0.08
    },
    "putin-out-before-2027": {
      "volumeNum": 4270273.573890949,
      "volume24hr": 24179.306126,
      "lastTradePrice": 0.12
    },
    "will-us-withdraw-from-nato-by-april-30-583-663": {
      "volumeNum": 4084394.871832998,
      "volume24hr": 33005.639737,
      "lastTradePrice": 0.003
    },
    "will-russia-invade-a-nato-country-by-june-30-2026": {
      "volumeNum": 2506310.3076699898,
      "volume24hr": 9165.266733,
      "lastTradePrice": 0.029
    },
    "zelenskyy-out-as-ukraine-president-before-2027": {
      "volumeNum": 2145269.8256809926,
      "volume24hr": 2168.7023779999995,
      "lastTradePrice": 0.15
    },
    "putin-out-as-president-of-russia-by-june-30": {
      "volumeNum": 1386239.8248270124,
      "volume24hr": 7828.357173000001,
      "lastTradePrice": 0.029
    },
    "ukraine-joins-nato-before-2027": {
      "volumeNum": 1126126.2633320019,
      "volume24hr": 187.26,
      "lastTradePrice": 0.023
    },
    "will-trump-and-putin-meet-next-in-another-european-country-954-837-364": {
      "volumeNum": 962907.2723310008,
      "volume24hr": 213.87,
      "lastTradePrice": 0.007
    },
    "will-us-withdraw-from-nato-before-2027-348-975-598-224-737": {
      "volumeNum": 937249.237555,
      "volume24hr": 423.474872,
      "lastTradePrice": 0.117
    },
    "russia-x-ukraine-ceasefire-by-may-31-2026": {
      "volumeNum": 866165.6957000025,
      "volume24hr": 33075.438675,
      "lastTradePrice": 0.041
    },
    "will-trump-and-putin-not-meet-315-857-437-514": {
      "volumeNum": 809389.9813200007,
      "volume24hr": 766.1675129999999,
      "lastTradePrice": 0.833
    },
    "will-trump-and-putin-meet-next-in-russia-594-493-482": {
      "volumeNum": 658221.9596380003,
      "volume24hr": 535.3921620000001,
      "lastTradePrice": 0.021
    },
    "will-ukraine-agree-to-cede-territory-to-russia-before-2027": {
      "volumeNum": 559894.6778270004,
      "volume24hr": 629.180453,
      "lastTradePrice": 0.12
    },
    "will-trump-and-putin-meet-next-in-another-country-313-781-734-447": {
      "volumeNum": 444943.93471200025,
      "volume24hr": 685.801111,
      "lastTradePrice": 0.013
    },
    "nato-x-russia-military-clash-by-june-30-2026": {
      "volumeNum": 439080.303068,
      "volume24hr": 304.408771,
      "lastTradePrice": 0.067
    },
    "will-zelenskyy-and-putin-meet-next-in-us": {
      "volumeNum": 437250.68240399973,
      "volume24hr": 309.9,
      "lastTradePrice": 0.013
    },
    "russia-x-ukraine-peace-parlay": {
      "volumeNum": 423335.5059329998,
      "volume24hr": 56.46882,
      "lastTradePrice": 0.15
    },
    "ukraine-election-held-by-june-30-2026-465-757": {
      "volumeNum": 386137.716611,
      "volume24hr": 175.364692,
      "lastTradePrice": 0.021
    },
    "will-trump-and-putin-meet-next-in-turkey-182-161-789": {
      "volumeNum": 382737.9596960002,
      "volume24hr": 91.7206,
      "lastTradePrice": 0.009
    },
    "eunato-country-announces-peacekeeping-force-in-ukraine-before-2027": {
      "volumeNum": 380900.69094999996,
      "volume24hr": 2066.27,
      "lastTradePrice": 0.02
    },
    "ukraine-recognizes-russian-sovereignty-over-its-territory-by-june-30-2026": {
      "volumeNum": 356867.5596360004,
      "volume24hr": 5997.026665,
      "lastTradePrice": 0.019
    },
    "will-zelenskyy-and-putin-meet-next-in-qatar-uae": {
      "volumeNum": 347503.03032200015,
      "volume24hr": 3889,
      "lastTradePrice": 0.029
    },
    "will-trump-and-putin-meet-next-in-belarus-572": {
      "volumeNum": 338648.414881,
      "volume24hr": 25,
      "lastTradePrice": 0.007
    },
    "will-trump-and-putin-meet-next-in-china-586-328": {
      "volumeNum": 307947.2907270002,
      "volume24hr": 435.444799,
      "lastTradePrice": 0.058
    },
    "will-trump-and-putin-meet-next-in-a-gulf-country-733-116": {
      "volumeNum": 270211.63539899985,
      "volume24hr": 25,
      "lastTradePrice": 0.007
    },
    "will-zelenskyy-and-putin-meet-next-in-belarus": {
      "volumeNum": 265315.94725300005,
      "volume24hr": 20,
      "lastTradePrice": 0.003
    },
    "ukraine-peace-referendum-scheduled-by-june-30": {
      "volumeNum": 250990.19288199997,
      "volume24hr": 100,
      "lastTradePrice": 0.05
    },
    "ukraine-election-called-by-june-30-2026-392": {
      "volumeNum": 233625.62326199966,
      "volume24hr": 1024.372119,
      "lastTradePrice": 0.031
    },
    "will-trump-and-putin-meet-next-in-united-states-224-875-469": {
      "volumeNum": 230691.93842799994,
      "volume24hr": 4191.71,
      "lastTradePrice": 0.012
    },
    "will-putin-meet-with-zelenskyy-by-june-30-2026": {
      "volumeNum": 216078.28857100013,
      "volume24hr": 389.819997,
      "lastTradePrice": 0.042
    },
    "ukraine-signs-peace-deal-with-russia-before-2027": {
      "volumeNum": 204949.3414030001,
      "volume24hr": 220.10190200000002,
      "lastTradePrice": 0.28
    },
    "will-russia-capture-slovainsk-by-2027": {
      "volumeNum": 204379.36279399978,
      "volume24hr": 1856.01,
      "lastTradePrice": 0.046
    },
    "will-zelenskyy-and-putin-meet-next-in-ukraine": {
      "volumeNum": 184913.45451100008,
      "volume24hr": 20,
      "lastTradePrice": 0.001
    },
    "ukraine-election-held-by-december-31-2026-344-142": {
      "volumeNum": 184336.92308399983,
      "volume24hr": 139.08695,
      "lastTradePrice": 0.11
    },
    "will-zelenskyy-and-putin-meet-next-in-india-416-286": {
      "volumeNum": 166826.93151700002,
      "volume24hr": 20,
      "lastTradePrice": 0.005
    },
    "will-trump-and-putin-meet-next-in-ukraine-328-474": {
      "volumeNum": 164581.95471399996,
      "volume24hr": 691.66,
      "lastTradePrice": 0.002
    },
    "will-trump-and-putin-meet-next-in-switzerland-448-348": {
      "volumeNum": 162876.01874700014,
      "volume24hr": 25,
      "lastTradePrice": 0.003
    },
    "will-zelenskyy-and-putin-meet-next-in-switzerland-848-193": {
      "volumeNum": 155519.28677700003,
      "volume24hr": 20,
      "lastTradePrice": 0.009
    },
    "zelenskyy-out-as-ukraine-president-by-january-31-2026": {
      "volumeNum": 153104.85753599982,
      "volume24hr": 128.993166,
      "lastTradePrice": 0.03
    },
    "us-agrees-to-give-ukraine-security-guarantee-by-june-30": {
      "volumeNum": 144061.32510200003,
      "volume24hr": 1829.92,
      "lastTradePrice": 0.06
    },
    "will-trump-and-putin-meet-next-in-japan-711-288-527": {
      "volumeNum": 140723.68432800006,
      "volume24hr": 2011.6599999999999,
      "lastTradePrice": 0.002
    },
    "will-trump-and-putin-meet-next-in-australia-459-332-211": {
      "volumeNum": 133131.92133499996,
      "volume24hr": 691.66,
      "lastTradePrice": 0.002
    },
    "will-trump-and-putin-meet-next-in-south-korea-582-297-268": {
      "volumeNum": 133054.31655800005,
      "volume24hr": 2271.8,
      "lastTradePrice": 0.002
    },
    "will-zelenskyy-and-putin-meet-next-in-turkey": {
      "volumeNum": 131583.20396400001,
      "volume24hr": 676.171557,
      "lastTradePrice": 0.027
    },
    "will-zelenskyy-and-putin-not-meet": {
      "volumeNum": 129810.3860609999,
      "volume24hr": 107.44411299999999,
      "lastTradePrice": 0.84
    },
    "will-zelenskyy-and-putin-meet-next-in-russia": {
      "volumeNum": 128748.64267899998,
      "volume24hr": 120.01,
      "lastTradePrice": 0.006
    },
    "european-country-agrees-to-give-ukraine-security-guarantee-by-june-30": {
      "volumeNum": 110098.35306100003,
      "volume24hr": 18.413369,
      "lastTradePrice": 0.07
    },
    "russia-x-ukraine-ceasefire-by-end-of-2027": {
      "volumeNum": 108294.5944050009,
      "volume24hr": 12056.284898999998,
      "lastTradePrice": 0.51
    },
    "natoeu-troops-fighting-in-ukraine-in-june-30-2026": {
      "volumeNum": 107749.0091480002,
      "volume24hr": 47.86,
      "lastTradePrice": 0.025
    },
    "will-trump-and-putin-meet-next-in-finland-772-412": {
      "volumeNum": 98635.7839049997,
      "volume24hr": 4631.66,
      "lastTradePrice": 0.002
    },
    "ukraine-signs-peace-deal-with-russia-by-june-30": {
      "volumeNum": 97958.55742699998,
      "volume24hr": 638.53,
      "lastTradePrice": 0.06
    },
    "will-zelenskyy-and-putin-meet-next-in-saudi-arabia": {
      "volumeNum": 96205.79958900005,
      "volume24hr": 60,
      "lastTradePrice": 0.014
    },
    "will-us-withdraw-from-nato-by-june-30": {
      "volumeNum": 92899.74567799999,
      "volume24hr": 3834.970439,
      "lastTradePrice": 0.031
    },
    "ukraine-agrees-to-limit-size-of-armed-forces-before-2027": {
      "volumeNum": 90933.77226200003,
      "volume24hr": 936.6875239999999,
      "lastTradePrice": 0.18
    },
    "will-zelenskyy-and-putin-meet-next-in-kazakhstan-485-344": {
      "volumeNum": 88432.89216700004,
      "volume24hr": 20,
      "lastTradePrice": 0.013
    },
    "ukraine-agrees-not-to-join-nato-before-2027": {
      "volumeNum": 85528.85628700009,
      "volume24hr": 80.404817,
      "lastTradePrice": 0.17
    },
    "will-zelenskyy-and-putin-meet-next-in-italy-vatican": {
      "volumeNum": 77242.42356400001,
      "volume24hr": 20,
      "lastTradePrice": 0.003
    },
    "will-ukraine-agree-to-give-up-the-rest-of-donbas-before-2027": {
      "volumeNum": 67483.798351,
      "volume24hr": 21.78888,
      "lastTradePrice": 0.09
    },
    "nato-x-russia-military-clash-by-december-31-2026-244": {
      "volumeNum": 59880.74693300001,
      "volume24hr": 406.733938,
      "lastTradePrice": 0.2
    },
    "russia-x-ukraine-ceasefire-by-june-30-2027": {
      "volumeNum": 50457.38234700002,
      "volume24hr": 10747.391873,
      "lastTradePrice": 0.42
    },
    "will-zelenskyy-and-putin-meet-next-in-hungary": {
      "volumeNum": 47630.65058600008,
      "volume24hr": 98.8,
      "lastTradePrice": 0.004
    },
    "us-recognizes-russian-sovereignty-over-ukraine-before-2027": {
      "volumeNum": 40253.25169700002,
      "volume24hr": 886.275713,
      "lastTradePrice": 0.21
    },
    "ukraine-recognizes-russian-sovereignty-over-its-territory-by-december-31-2026": {
      "volumeNum": 38775.239296000014,
      "volume24hr": 348.48999000000003,
      "lastTradePrice": 0.1
    },
    "ukraine-officially-agrees-to-a-us-backed-ceasefire-framework-by-june-30": {
      "volumeNum": 38106.168179999986,
      "volume24hr": 12.478125,
      "lastTradePrice": 0.1
    },
    "will-zelenskyy-and-putin-meet-next-in-china": {
      "volumeNum": 34782.25863300001,
      "volume24hr": 20,
      "lastTradePrice": 0.009
    },
    "ukraine-agrees-not-to-join-nato-by-june-30": {
      "volumeNum": 29589.16455100001,
      "volume24hr": 105.64,
      "lastTradePrice": 0.037
    },
    "us-x-russia-nuclear-deal-by-june-30": {
      "volumeNum": 29446.181843000028,
      "volume24hr": 0,
      "lastTradePrice": 0.07
    },
    "will-the-us-test-a-nuclear-weapon-by-june-30-2026": {
      "volumeNum": 24401.295366000002,
      "volume24hr": 0,
      "lastTradePrice": 0.017
    },
    "will-zelenskyy-talk-to-putin-by-december-31-992": {
      "volumeNum": 22258.39806800001,
      "volume24hr": 6.59,
      "lastTradePrice": 0.24
    },
    "trump-putin-and-zelensky-meet-together-before-2027": {
      "volumeNum": 17375.659326000008,
      "volume24hr": 18.809842,
      "lastTradePrice": 0.17
    },
    "ukraine-hits-moscow-by-april-30-2026": {
      "volumeNum": 17236.909360999998,
      "volume24hr": 592.854263,
      "lastTradePrice": 0.055
    },
    "will-russia-rejoin-the-g7-before-2027": {
      "volumeNum": 13599.926465,
      "volume24hr": 384.17,
      "lastTradePrice": 0.06
    },
    "will-russia-test-a-nuclear-weapon-by-december-31-2026-75zh": {
      "volumeNum": 12794.256493000003,
      "volume24hr": 615.63722,
      "lastTradePrice": 0.1
    },
    "ukraine-peace-referendum-passed-by-december-31-2026": {
      "volumeNum": 10773.397286000001,
      "volume24hr": 6.176469,
      "lastTradePrice": 0.17
    },
    "nord-stream-pipeline-turned-on-before-2027": {
      "volumeNum": 9545.785152000002,
      "volume24hr": 311.74,
      "lastTradePrice": 0.07
    },
    "ukraine-coup-attempt-by-june-30": {
      "volumeNum": 9099.374223,
      "volume24hr": 0,
      "lastTradePrice": 0.03
    },
    "putin-and-zelenskyy-shake-hands-by-june-30": {
      "volumeNum": 9099.115490999999,
      "volume24hr": 1.568612,
      "lastTradePrice": 0.035
    },
    "trump-putin-and-zelensky-seen-together-before-2027": {
      "volumeNum": 8059.911780999998,
      "volume24hr": 101.12359,
      "lastTradePrice": 0.12
    },
    "will-russia-test-a-nuclear-weapon-by-june-30-2026": {
      "volumeNum": 7101.737322,
      "volume24hr": 606.959652,
      "lastTradePrice": 0.023
    },
    "will-a-us-ally-get-a-nuke-before-2027": {
      "volumeNum": 6397.7462989999985,
      "volume24hr": 8.034863,
      "lastTradePrice": 0.16
    },
    "will-the-us-test-a-nuclear-weapon-by-december-31-2026": {
      "volumeNum": 5478.56042,
      "volume24hr": 1204.539089,
      "lastTradePrice": 0.13
    },
    "eunato-country-announces-peacekeeping-force-in-ukraine-by-december-31": {
      "volumeNum": 4737.827500999997,
      "volume24hr": 223.45212700000002,
      "lastTradePrice": 0.12
    },
    "will-the-us-test-a-nuclear-weapon-by-september-30-2026": {
      "volumeNum": 2430.097802000001,
      "volume24hr": 108.095788,
      "lastTradePrice": 0.05
    },
    "will-russia-test-a-nuclear-weapon-by-september-30-2026": {
      "volumeNum": 2057.0593070000004,
      "volume24hr": 320.38,
      "lastTradePrice": 0.09
    },
    "ukraine-peace-referendum-scheduled-by-december-31": {
      "volumeNum": 63.535109999999996,
      "volume24hr": 0,
      "lastTradePrice": 0.3
    },
    "ukraine-peace-referendum-scheduled-by-september-30": {
      "volumeNum": 39.129118999999996,
      "volume24hr": 0,
      "lastTradePrice": 0.05
    },
    "will-donald-trump-win-the-nobel-peace-prize-in-2026-382": {
      "volumeNum": 2595169.572143021,
      "volume24hr": 14714.417085000001,
      "lastTradePrice": 0.07
    },
    "will-unrwa-win-the-nobel-peace-prize-in-2026-983": {
      "volumeNum": 1887168.4362159981,
      "volume24hr": 3960.9965640000005,
      "lastTradePrice": 0.035
    },
    "will-ukraine-win-eurovision-2026": {
      "volumeNum": 1822753.017009998,
      "volume24hr": 28927.150599,
      "lastTradePrice": 0.019
    },
    "russia-ukraine-ceasefire-before-gta-vi-554": {
      "volumeNum": 1618251.874264044,
      "volume24hr": 11801.267821000025,
      "lastTradePrice": 0.53
    },
    "will-greta-thunberg-win-the-nobel-peace-prize-in-2026-767": {
      "volumeNum": 1117729.2768189935,
      "volume24hr": 546.554932,
      "lastTradePrice": 0.025
    },
    "will-xi-jinping-win-the-nobel-peace-prize-in-2026": {
      "volumeNum": 932044.304038999,
      "volume24hr": 28.246861000000003,
      "lastTradePrice": 0.039
    },
    "will-charlie-kirk-win-the-nobel-peace-prize-in-2026": {
      "volumeNum": 759457.5334880003,
      "volume24hr": 6380.887158,
      "lastTradePrice": 0.012
    },
    "will-the-international-court-of-justice-win-the-nobel-peace-prize-in-2026-885": {
      "volumeNum": 713505.374694001,
      "volume24hr": 2141.108328,
      "lastTradePrice": 0.033
    },
    "will-ahmed-al-sharaa-win-the-nobel-peace-prize-in-2026": {
      "volumeNum": 712403.1722299986,
      "volume24hr": 1498.4303840000002,
      "lastTradePrice": 0.012
    },
    "will-mohammed-bin-salman-win-the-nobel-peace-prize-in-2026": {
      "volumeNum": 681342.8461799998,
      "volume24hr": 407.1261,
      "lastTradePrice": 0.009
    },
    "will-pope-leo-xiv-win-the-nobel-peace-prize-in-2026-698": {
      "volumeNum": 663403.168463001,
      "volume24hr": 169.220768,
      "lastTradePrice": 0.052
    },
    "will-elon-musk-win-the-nobel-peace-prize-in-2026-756": {
      "volumeNum": 569911.7567799977,
      "volume24hr": 552.3691999999999,
      "lastTradePrice": 0.013
    },
    "will-recep-tayyip-erdoan-win-the-nobel-peace-prize-in-2026": {
      "volumeNum": 569507.4383980011,
      "volume24hr": 0,
      "lastTradePrice": 0.013
    },
    "will-tamim-bin-hamad-al-thani-win-the-nobel-peace-prize-in-2026-755": {
      "volumeNum": 564334.0958210023,
      "volume24hr": 2692.396649999999,
      "lastTradePrice": 0.034
    },
    "will-vladimir-putin-win-the-nobel-peace-prize-in-2026-126": {
      "volumeNum": 545918.7157269998,
      "volume24hr": 46.627666,
      "lastTradePrice": 0.007
    },
    "will-narendra-modi-win-the-nobel-peace-prize-in-2026": {
      "volumeNum": 450005.7389439996,
      "volume24hr": 4988.627653000001,
      "lastTradePrice": 0.016
    },
    "will-vladimir-putin-be-the-next-leader-out-before-2027-919": {
      "volumeNum": 449433.89208699996,
      "volume24hr": 1961.501666,
      "lastTradePrice": 0.001
    },
    "will-volodymyr-zelensky-win-the-nobel-peace-prize-in-2026-637": {
      "volumeNum": 430067.5577889996,
      "volume24hr": 2083.711707,
      "lastTradePrice": 0.09
    },
    "will-julian-assange-win-the-nobel-peace-prize-in-2026-899": {
      "volumeNum": 374991.0131319993,
      "volume24hr": 25.86,
      "lastTradePrice": 0.008
    },
    "will-benjamin-netanyahu-win-the-nobel-peace-prize-in-2026": {
      "volumeNum": 372468.21486899914,
      "volume24hr": 0,
      "lastTradePrice": 0.008
    },
    "will-khaled-mashal-win-the-nobel-peace-prize-in-2026-787": {
      "volumeNum": 307190.7755059998,
      "volume24hr": 3613.5621910000004,
      "lastTradePrice": 0.009
    },
    "will-antnio-guterres-win-the-nobel-peace-prize-in-2026-623": {
      "volumeNum": 279265.4776009996,
      "volume24hr": 205.68908900000002,
      "lastTradePrice": 0.009
    },
    "will-yulia-navalnaya-win-the-nobel-peace-prize-in-2026-261": {
      "volumeNum": 130843.55196499855,
      "volume24hr": 1753.595453,
      "lastTradePrice": 0.1
    },
    "will-volodymyr-zelenskyy-be-the-next-leader-out-before-2027-426": {
      "volumeNum": 117978.591113,
      "volume24hr": 4434.390179000001,
      "lastTradePrice": 0.014
    }
  }
}